Workbook

Sheet Résumé de l’exportation
B3: Ce document a été exporté depuis Numbers. Chaque tableau a été converti en feuille de calcul Excel. Tous les autres objets sur chaque feuille Numbers ont été placés sur des feuilles de calcul différentes. Veuillez noter que les calculs de formules peuvent être différents dans Excel.
B7: Nom de la feuille Numbers | C7: Nom du tableau Numbers | D7: Nom de la feuille de calcul Excel
B9: Plan d'actions
C10: Tableau 1 | D10: Plan d'actions
B11: Programme
C12: Tableau 1 | D12: Programme
B13: Budget
C14: Budget | D14: Budget - Budget
C15: Dépenses réelles | D15: Budget - Dépenses réelles
B16: Invités
C17: Tableau 1 | D17: Invités
B18: Témoins & Honneurs
C19: Tableau 1 | D19: Témoins & Honneurs - Tableau 1
C20: Tableau 1-1 | D20: Témoins & Honneurs - Tableau 1-
B21: EVJF & EVG
C22: Léa | D22: EVJF & EVG - Léa
C23: PA | D23: EVJF & EVG - PA
B24: Lieu
C25: Tableau 1 | D25: Lieu
B26: Repas
C27: Tableau 1 | D27: Repas - Tableau 1
C28: Gauthier traiteur | D28: Repas - Gauthier traiteur
C29: Devis Food Truck | D29: Repas - Devis Food Truck
C30: Devis Brunch | D30: Repas - Devis Brunch
B31: Couchages
C32: Lodge | D32: Couchages - Lodge
C33: Maison | D33: Couchages - Maison
C34: Cabane | D34: Couchages - Cabane
C35: Tipis | D35: Couchages - Tipis
B36: Photos & Vidéos
C37: Tableau 1 | D37: Photos & Vidéos - Tableau 1
C38: Groupe photos | D38: Photos & Vidéos - Groupe photos
B39: Musique
C40: Tableau 1 | D40: Musique
B41: Activités
C42: Tableau 1 | D42: Activités - Tableau 1
C43: Devis Coordinatrice | D43: Activités - Devis Coordinatrice
B44: Habillement
C45: Tableau 1 | D45: Habillement
B46: Voiture
C47: Tableau 1 | D47: Voiture
B48: Décorations
C49: Tableau 1 | D49: Décorations - Tableau 1
C50: Devis Fleuriste | D50: Décorations - Devis Fleuriste
B51: Coiffure/Maquillage
C52: Devis Makeup | D52: Coiffure_Maquillage - Devis Mak
C53: Devis Coiffure | D53: Coiffure_Maquillage - Devis Coi
B54: Alliances
C55: Tableau 1 | D55: Alliances
B56: Notaire
C57: Tableau 1 | D57: Notaire
B58: Lune de miel
C59: Tableau 1 | D59: Lune de miel
B60: Cérémonie mairie
C61: Tableau 1 | D61: Cérémonie mairie
B62: Cérémonie religieuse
C63: Budget | D63: Cérémonie religieuse - Budget

Sheet Plan d'actions
A1: Tâche | B1: ETA | C1: Responsable | D1: Statut
A2: Cocher les invités éligibles aux faire-part | B2: 46047 | C2: Léa GINTZ | D2: Terminé
A3: Cocher les invités éligibles aux faire-part | B3: 46047 | C3: Pierre-Alexandre COUBARD | D3: En cours
A4: Réserver les visites de lieux | B4: 46054 | C4: Léa GINTZ & Pierre-Alexandre COUBARD | D4: Terminé
A5: Faire un premier modèle de faire-part digital | B5: 46068 | C5: Léa GINTZ | D5: Terminé
A6: Rechercher les prestataires de brunch | B6: 46081 | C6: Léa GINTZ | D6: En cours
A7: Faire la liste des VIP | B7: 46081 | C7: Léa GINTZ & Pierre-Alexandre COUBARD | D7: Terminé
A8: Trouver église | B8: 46113 | C8: Léa GINTZ | D8: Terminé
A9: Remplir tableau invités (adresse, tel, mail) | B9: 46127 | C9: Léa GINTZ & Pierre-Alexandre COUBARD | D9: En cours
A10: Première ébauche programme | B10: 46127 | C10: Pierre-Alexandre COUBARD | D10: En cours
A11: Valider la répartition hébergements | B11: 46127 | C11: Pierre-Alexandre COUBARD | D11: En cours
A12: Finir le site internet | B12: 46142 | C12: Pierre-Alexandre COUBARD | D12: Non commencé
A13: Faire dossier mariage église | B13: 46169 | C13: Léa GINTZ | D13: En cours
... A43: Envoyer les remerciements à tous les invités | B43: 46629 | C43: Léa GINTZ | D43: Non commencé
A81: Tâches restantes | B81: {=COUNTA($C$2:$C$41)-COUNTIF($C$2:$C$41,"Terminé")} -> 40 | C81: Travail fait —> | D81: {=_xlfn.IFERROR(COUNTIF($D$2:$D$80,"Terminé")/COUNTA($D$2:$D$80),0%)} -> 0.23809524

Sheet Programme
A1: ORGANISATION
A2: Date | B2: Heure début | C2: Heure fin | D2: Activité | E2: Responsable | F2: Lieu | G2: Remarques
A3: Vendredi 13 août 2027 | B3: 08h00 | C3: 08h00 | D3: Récupération de la Porsche à Sartrouville | E3: PA | F3: Sartrouville
B4: 11h00 | C4: 11h30 | D4: Cérémonie civile — mairie | E4: Léa & PA | F4: Mairie de Sillé-le-Guillaume
B5: 11h30 | C5: 13h00 | D5: Déjeuner au restaurant | E5: TBD | F5: Sillé-le-Guillaume
B6: 13h00 | C6: 15h30 | D6: Route vers le Domaine de Meaucé | E6: PA | F6: Domaine de Meaucé
B7: 14h00 | C7: 14h00 | D7: Récupération du domaine | E7: Léa & PA | F7: Domaine de Meaucé
B8: 19h00 | C8: 22h00 | D8: Dîner Tarte Flambée | E8: Flamman | F8: Domaine de Meaucé
A9: Samedi 14 août 2027 | B9: TBF | C9: TBF | D9: Petit-déjeuner du samedi matin | E9: Domaine | F9: Domaine de Meaucé
B10: 08h30 | C10: 09h00 | D10: Arrivée coiffure / maquillage | E10: Coiffeuse & maquilleuse | F10: Domaine de Meaucé
B11: 09h00 | C11: 09h00 | D11: Arrivée de Tiphany — installation générale | E11: Tiphany + assistante | F11: Domaine de Meaucé
B12: 09h00 | C12: 12h30 | D12: Préparatifs Léa | E12: Léa, coiffeuse, témoins, photographe, vidéaste | F12: Domaine de Meaucé
B13: 09h00 | C13: 11h00 | D13: Préparatifs PA | E13: PA, témoins, photographe, vidéaste | F13: Domaine de Meaucé
B14: 12h00 | C14: 12h45 | D14: Déjeuner léger du samedi midi | E14: Libre | F14: Domaine de Meaucé
B15: 13h00 | C15: 13h00 | D15: Habillage final | E15: Léa & PA | F15: Domaine de Meaucé
B16: 13h30 | C16: 13h30 | D16: Départ vers l'église | E16: Chauffeur LRM | F16: Domaine → Église
B17: 13h30 | C17: 14h45 | D17: Accueil des invités à l'église | E17: Tiphany + assistante | F17: Église Saint-Pierre de Manou
B18: 14h45 | C18: 14h45 | D18: Arrivée de PA à l'église | E18: PA, Constance | F18: Église Saint-Pierre de Manou
B19: 46243.622 | C19: 46243.625 | D19: Arrivée de Léa à l'église | E19: Léa, Christophe G | F19: Église Saint-Pierre de Manou
B20: 15h00 | C20: 16h00 | D20: Cérémonie religieuse | F20: Église Saint-Pierre de Manou
B21: 16h00 | C21: 16h40 | D21: Sortie & photos de groupe prioritaires | E21: Photographe, vidéaste | F21: Église (parvis)
B22: 16h40 | C22: 46243.708 | D22: Retour vers le domaine
B23: 46243.708 | C23: 46243.729 | D23: Accueil soft par traiteur, installations pour ceux qui dorment sur place, photo pour Léa & PA | E23: Tiphany
B24: 46243.729 | C24: 46243.75 | D24: Photos | E24: Photographe, vidéaste
B25: 46243.75 | C25: 19h30 | D25: Vin d'honneur | E25: Traiteur, MV, Rachel Wong | F25: Domaine de Meaucé
B26: 19h30 | C26: 46243.833 | D26: Photos de groupe et passage a table | E26: Tiphany | F26: Domaine de Meaucé
B27: 20h00 | C27: 22h00 | D27: Dîner assis & discours | E27: Traiteur, famille, amis | F27: Domaine de Meaucé
B28: 46244.896 | C28: 46244.917 | D28: Changement de robe Léa
B29: 22h00 | C29: 22h05 | D29: Première danse | E29: DJ | F29: Domaine de Meaucé
B30: 22h05 | C30: 23h05 | D30: Concert live Seven Ages (1h) | E30: Seven Ages | F30: Domaine de Meaucé
B31: 23h05 | C31: 23h30 | D31: Dessert | E31: Traiteur | F31: Domaine de Meaucé
B32: 23h30 | C32: 04h00 | D32: Soirée dansante | E32: DJ | F32: Domaine de Meaucé
B33: 46243.188 | D33: Coupure de la musique | E33: DJ | F33: Domaine de Meaucé
B34: 04h00 | C34: 05h00 | D34: Fin de soirée | F34: Domaine de Meaucé
A35: Dimanche 15 août 2027 | B35: 09h00 | C35: 11h00 | D35: Petit-déjeuner | E35: Domaine (inclus) | F35: Domaine de Meaucé
B36: 11h00 | C36: 15h00 | D36: Pool party — piscine, brunch & DJ set | E36: DJ, traiteur brunch | F36: Domaine de Meaucé
B37: 15h00 | C37: 15h30 | D37: Temps libre & début du rangement | E37: Familles et témoins | F37: Domaine de Meaucé
B38: 15h30 | C38: 16h00 | D38: Check-out des tipis | E38: Invités des tipis | F38: Domaine de Meaucé
B39: 16h00 | C39: 16h30 | D39: Check-out du lodge | E39: Invités du lodge | F39: Domaine de Meaucé
B40: 16h30 | C40: 17h00 | D40: Check-out de la maison & fin piscine/salles | E40: Léa & PA | F40: Domaine de Meaucé
B41: 18h00 | C41: 18h00 | D41: Fin de la location | E41: Léa & PA | F41: Domaine de Meaucé

Sheet Budget - Budget
A1: Budget
A2: Catégorie | B2: Budget initial | C2: Budget révisé | D2: Delta | E2: Réel | F2: Delta
A3: Repas | B3: 12000 | C3: {='Repas - Tableau 1'!C$34} -> 16904.911 | D3: {=_xlfn.IFERROR(C3/B3-1,0)} -> 0.40874258 | E3: {=SUMIF('Budget - Dépenses réelles'!A3:A31,$A3,'Budget - Dépenses réelles'!D3:D31)} -> 284 | F3: {=_xlfn.IFERROR(E3/C3-1,0)} -> -0.98320015
A4: Réception | B4: 10000 | C4: {='Lieu'!M4} -> 13933.2 | D4: {=_xlfn.IFERROR(C4/B4-1,0)} -> 0.39332 | E4: {=SUMIF('Budget - Dépenses réelles'!A3:A31,$A4,'Budget - Dépenses réelles'!D3:D31)} -> 6000 | F4: {=_xlfn.IFERROR(E4/C4-1,0)} -> -0.56937387
A5: Habillement | B5: 2000 | C5: {='Habillement'!B$14} -> 7030 | D5: {=_xlfn.IFERROR(C5/B5-1,0)} -> 2.515 | E5: {=SUMIF('Budget - Dépenses réelles'!A3:A31,$A5,'Budget - Dépenses réelles'!D3:D31)} -> 0 | F5: {=_xlfn.IFERROR(E5/C5-1,0)} -> -1
A6: Lune de miel | B6: 10000 | C6: {='Lune de miel'!B$5} -> 5000 | D6: {=_xlfn.IFERROR(C6/B6-1,0)} -> -0.5 | E6: {=SUMIF('Budget - Dépenses réelles'!A3:A31,$A6,'Budget - Dépenses réelles'!D3:D31)} -> 0 | F6: {=_xlfn.IFERROR(E6/C6-1,0)} -> -1
A7: Musique | B7: 2000 | C7: {='Musique'!C$6} -> 3833.34 | D7: {=_xlfn.IFERROR(C7/B7-1,0)} -> 0.91667 | E7: {=SUMIF('Budget - Dépenses réelles'!A3:A31,$A7,'Budget - Dépenses réelles'!D3:D31)} -> 941 | F7: {=_xlfn.IFERROR(E7/C7-1,0)} -> -0.75452217
A8: Décoration | B8: 3000 | C8: {='Décorations - Tableau 1'!C$10} -> 2985.8 | D8: {=_xlfn.IFERROR(C8/B8-1,0)} -> -0.0047333333 | E8: {=SUMIF('Budget - Dépenses réelles'!A3:A31,$A8,'Budget - Dépenses réelles'!D3:D31)} -> 0 | F8: {=_xlfn.IFERROR(E8/C8-1,0)} -> -1
A9: Alliances | B9: 4000 | C9: {='Alliances'!B$6} -> 2430 | D9: {=_xlfn.IFERROR(C9/B9-1,0)} -> -0.3925 | E9: {=SUMIF('Budget - Dépenses réelles'!A3:A31,$A9,'Budget - Dépenses réelles'!D3:D31)} -> 0 | F9: {=_xlfn.IFERROR(E9/C9-1,0)} -> -1
A10: Activités | B10: 1000 | C10: {='Activités - Tableau 1'!B$8} -> 2209 | D10: {=_xlfn.IFERROR(C10/B10-1,0)} -> 1.209 | E10: {=SUMIF('Budget - Dépenses réelles'!A3:A31,$A10,'Budget - Dépenses réelles'!D3:D31)} -> 479.6 | F10: {=_xlfn.IFERROR(E10/C10-1,0)} -> -0.78288818
A11: Photos & Vidéos | B11: 2500 | C11: {='Photos & Vidéos - Tableau 1'!C$5} -> 2117 | D11: {=_xlfn.IFERROR(C11/B11-1,0)} -> -0.1532 | E11: {=SUMIF('Budget - Dépenses réelles'!A3:A31,$A11,'Budget - Dépenses réelles'!D3:D31)} -> 106 | F11: {=_xlfn.IFERROR(E11/C11-1,0)} -> -0.94992915
A12: Voiture | B12: 500 | C12: {='Voiture'!C$4} -> 1250 | D12: {=_xlfn.IFERROR(C12/B12-1,0)} -> 1.5 | E12: {=SUMIF('Budget - Dépenses réelles'!A3:A31,$A12,'Budget - Dépenses réelles'!D3:D31)} -> 190 | F12: {=_xlfn.IFERROR(E12/C12-1,0)} -> -0.848
A13: Coiffure et maquillage | B13: 1500 | C13: {='Coiffure_Maquillage - Devis Mak'!C8} -> 830 | D13: {=_xlfn.IFERROR(C13/B13-1,0)} -> -0.44666667 | E13: {=SUMIF('Budget - Dépenses réelles'!A3:A31,$A13,'Budget - Dépenses réelles'!D3:D31)} -> 0 | F13: {=_xlfn.IFERROR(E13/C13-1,0)} -> -1
A14: Cérémonie religieuse | B14: 600 | C14: 700 | D14: {=_xlfn.IFERROR(C14/B14-1,0)} -> 0.16666667 | E14: {=SUMIF('Budget - Dépenses réelles'!A3:A31,$A14,'Budget - Dépenses réelles'!D3:D31)} -> 0 | F14: {=_xlfn.IFERROR(E14/C14-1,0)} -> -1
A15: Cérémonie mairie | B15: 500 | C15: 500 | D15: {=_xlfn.IFERROR(C15/B15-1,0)} -> 0 | E15: {=SUMIF('Budget - Dépenses réelles'!A3:A31,$A15,'Budget - Dépenses réelles'!D3:D31)} -> 0 | F15: {=_xlfn.IFERROR(E15/C15-1,0)} -> -1
A16: Notaire | B16: 500 | C16: {='Notaire'!B$6} -> 378.98 | D16: {=_xlfn.IFERROR(C16/B16-1,0)} -> -0.24204 | E16: {=SUMIF('Budget - Dépenses réelles'!A3:A31,$A16,'Budget - Dépenses réelles'!D3:D31)} -> 0 | F16: {=_xlfn.IFERROR(E16/C16-1,0)} -> -1
A17: Cadeaux | B17: -5000 | C17: -5000 | D17: {=_xlfn.IFERROR(C17/B17-1,0)} -> 0 | E17: {=SUMIF('Budget - Dépenses réelles'!A3:A31,$A17,'Budget - Dépenses réelles'!D3:D31)} -> 0 | F17: {=_xlfn.IFERROR(E17/D17-1,0)} -> 0
A18: Total | B18: {=SUM(B3:B17)} -> 45100 | C18: {=SUM(C3:C17)} -> 55102.231 | D18: {=_xlfn.IFERROR(C18/B18-1,0)} -> 0.22177896 | E18: {=SUM(E3:E17)} -> 8000.6 | F18: {=_xlfn.IFERROR(E18/C18-1,0)} -> -0.85480443

Sheet Budget - Dépenses réelles
A1: Dépenses réelles
A2: Catégorie | B2: Description | C2: Date | D2: Montant | E2: Payeur
A3: Voiture | B3: Acompte LRM | C3: 45937 | D3: 190 | E3: PA
A4: Réception | B4: Acompte 1 | C4: 46107 | D4: 2000 | E4: Léa & PA
A5: Musique | B5: Acompte Maison Groovy | C5: 46133 | D5: 762 | E5: Léa & PA
A6: Activités | B6: Acompte Live Painting | C6: 46139 | D6: 100 | E6: Léa & PA
A7: Musique | B7: Acompte Seven Ages | C7: 46139 | D7: 55 | E7: Léa & PA
A8: Photos & Vidéos | B8: Acompte photographe | C8: 46140 | D8: 106 | E8: Léa & PA
A9: Réception | B9: Acompte 2 | C9: 46235 | D9: 4000 | E9: Léa & PA
A10: Musique | B10: Acompte MV | C10: 46240 | D10: 124 | E10: Léa & PA
A11: Activités | B11: Acompte Wedding Planner | C11: 46241 | D11: 379.6 | E11: Léa & PA
A12: Repas | B12: Acompte Flamm’Mann | C12: 46248 | D12: 284 | E12: Léa & PA
D32: {=SUM(D3:D31)} -> 8000.6

Sheet Invités
A1: Statut | B1: Nom | C1: Prénom | D1: Groupe | E1: Catégorie | F1: Adresse postale | G1: Adresse email | H1: Portable | I1: Faire-part digital | J1: Faire-part | K1: Confirmation | L1: Mairie | M1: Soirée accueil | N1: Église | O1: Repas | P1: Couchage | Q1: Placé couchage | R1: Alcool | S1: Brunch | T1: VIP | U1: Végétarien | V1: Témoins & Honneurs | W1: Lien
A2: Traité | B2: GINTZ | C2: Léa | D2: Mariés | E2: Adulte
A3: Traité | B3: COUBARD | C3: Pierre-Alexandre | D3: Mariés | E3: Adulte
A4: Traité | B4: GINTZ | C4: Christophe | D4: Famille Léa | E4: Adulte | F4: 66 rue de Saverne, 67370 Neugartheim-Ittlenheim | H4: 07 69 06 33 72 | I4: TRUE | J4: TRUE | K4: TRUE | L4: TRUE | M4: TRUE | N4: TRUE | O4: TRUE | P4: TRUE | Q4: TRUE | R4: TRUE | S4: TRUE | T4: TRUE | U4: FALSE | V4: FALSE | W4: Père Léa
A5: Traité | B5: GINTZ | C5: Alena | D5: Famille Léa | E5: Adulte | H5: 06 31 58 69 45 | I5: TRUE | J5: FALSE | K5: TRUE | L5: TRUE | M5: TRUE | N5: TRUE | O5: TRUE | P5: TRUE | Q5: TRUE | R5: FALSE | S5: TRUE | T5: TRUE | U5: FALSE | V5: FALSE | W5: Mère Léa
A6: Traité | B6: GINTZ | C6: Romain | D6: Famille Léa | E6: Adulte | H6: 07 68 68 22 01 | I6: TRUE | J6: FALSE | K6: TRUE | L6: TRUE | M6: TRUE | N6: TRUE | O6: TRUE | P6: TRUE | Q6: TRUE | R6: TRUE | S6: TRUE | T6: TRUE | U6: FALSE | V6: TRUE | W6: Frère Léa
A7: Traité | B7: GINTZ | C7: Amélie | D7: Famille Léa | E7: Adulte | H7: 07 66 87 23 25 | I7: TRUE | J7: FALSE | K7: TRUE | L7: TRUE | M7: TRUE | N7: TRUE | O7: TRUE | P7: TRUE | Q7: TRUE | R7: TRUE | S7: TRUE | T7: TRUE | U7: FALSE | V7: TRUE | W7: Soeur Léa
A8: En cours | B8: GINTZ | C8: Christianne | D8: Famille Léa | E8: Adulte | F8: 8 Rue de L’Église, 67370 Behlenheim-Truchtersheim | H8: 07 67 45 63 14 | I8: TRUE | J8: TRUE | K8: FALSE | L8: FALSE | M8: FALSE | N8: FALSE | O8: FALSE | P8: FALSE | Q8: FALSE | R8: FALSE | S8: FALSE | T8: FALSE | U8: FALSE | V8: FALSE | W8: Grand-mère Léa du cote de son père
A9: En cours | B9: GINTZ | C9: Michel | D9: Famille Léa | E9: Adulte | I9: TRUE | J9: FALSE | K9: FALSE | L9: FALSE | M9: FALSE | N9: FALSE | O9: FALSE | P9: FALSE | Q9: FALSE | R9: FALSE | S9: FALSE | T9: FALSE | U9: FALSE | V9: FALSE | W9: GRand-père Léa du cote de son pere
A10: Traité | B10: ZINCK | C10: Gaspard | D10: Famille Léa | E10: Adulte | H10: 07 67 80 36 70 | I10: TRUE | J10: FALSE | K10: TRUE | L10: TRUE | M10: TRUE | N10: TRUE | O10: TRUE | P10: TRUE | Q10: TRUE | R10: TRUE | S10: TRUE | T10: TRUE | U10: FALSE | V10: FALSE | W10: Copain d’Amélie la soeur de lléa
A11: En cours | B11: HABOUZIT | C11: Mélissande | D11: Famille Léa | E11: Adulte | H11: 06 38 36 15 46 | I11: TRUE | J11: FALSE | K11: TRUE | L11: TRUE | M11: TRUE | N11: TRUE | O11: TRUE | P11: TRUE | Q11: TRUE | R11: TRUE | S11: TRUE | T11: TRUE | U11: FALSE | V11: FALSE | W11: Copien de Romain frère de lea
A12: En cours | B12: BURANOVSKA | C12: Elisabeth | D12: Famille Léa | E12: Adulte | F12: Babka Buranovska Alzbeta Svabska 78 Presov 08001 République Slovaque | I12: TRUE | J12: TRUE | K12: FALSE | L12: FALSE | M12: FALSE | N12: FALSE | O12: FALSE | P12: FALSE | Q12: FALSE | R12: FALSE | S12: FALSE | T12: FALSE | U12: FALSE | V12: FALSE | W12: GRand mère de Léa du coté de sa mere
A13: En cours | B13: TKACOVY | C13: Jozef | D13: Famille Léa | E13: Adulte | F13: Jozef Tkac Podhradik 109 Podhradik 08006 République Slovaque | H13: +42 19 18 96 87 70 | I13: TRUE | J13: TRUE | K13: FALSE | L13: FALSE | M13: TRUE | N13: TRUE | O13: TRUE | P13: TRUE | Q13: TRUE | R13: TRUE | S13: TRUE | T13: FALSE | U13: FALSE | V13: FALSE | W13: ami du père de lea
A14: En cours | B14: TKACOVA | C14: Marta | D14: Famille Léa | E14: Adulte | I14: TRUE | J14: FALSE | K14: FALSE | L14: FALSE | M14: TRUE | N14: TRUE | O14: TRUE | P14: TRUE | Q14: TRUE | R14: FALSE | S14: TRUE | T14: FALSE | U14: FALSE | V14: FALSE | W14: Femme de Josef
A15: Traité | B15: GINTZ | C15: Laurence | D15: Famille Léa | E15: Adulte | F15: 1 rue des Acacias, 67270 Gougenheim | H15: 06 86 65 32 67 | I15: TRUE | J15: TRUE | K15: TRUE | L15: TRUE | M15: TRUE | N15: TRUE | O15: TRUE | P15: TRUE | Q15: TRUE | R15: FALSE | S15: TRUE | T15: TRUE | U15: FALSE | V15: FALSE | W15: Mariane de lea
A16: Traité | B16: GINTZ | C16: Marc | D16: Famille Léa | E16: Adulte | H16: 07 85 29 27 40 | I16: TRUE | J16: FALSE | K16: TRUE | L16: TRUE | M16: TRUE | N16: TRUE | O16: TRUE | P16: TRUE | Q16: TRUE | R16: TRUE | S16: TRUE | T16: TRUE | U16: FALSE | V16: FALSE | W16: Marie de Laurence Gintz
A17: Traité | B17: HILD | C17: Valérie | D17: Famille Léa | E17: Adulte | F17: 3 rue des Tilleuls, 67270 Gougenheim | H17: 06 38 60 61 69 | I17: TRUE | J17: TRUE | K17: TRUE | L17: TRUE | M17: TRUE | N17: TRUE | O17: TRUE | P17: TRUE | Q17: TRUE | R17: FALSE | S17: TRUE | T17: TRUE | U17: FALSE | V17: FALSE | W17: Soeur de la marraine de lea
A18: Traité | B18: JOURNOT | C18: Daniel | D18: Famille Léa | E18: Adulte | H18: 07 68 66 21 86 | I18: TRUE | J18: FALSE | K18: TRUE | L18: TRUE | M18: TRUE | N18: TRUE | O18: TRUE | P18: TRUE | Q18: TRUE | R18: TRUE | S18: TRUE | T18: TRUE | U18: FALSE | V18: FALSE | W18: Mari de Valérie
A19: En cours | B19: GINTZ | C19: Régis | D19: Famille Léa | E19: Adulte | F19: 11 rue kobler 67370 Dingsheim | H19: 06 70 21 98 92 | I19: TRUE | J19: TRUE | K19: FALSE | L19: FALSE | M19: TRUE | N19: TRUE | O19: TRUE | P19: TRUE | Q19: TRUE | R19: TRUE | S19: TRUE | T19: FALSE | U19: FALSE | V19: FALSE | W19: Oncle de lea du octe de osn pere
A20: En cours | B20: GINTZ | C20: Linda | D20: Famille Léa | E20: Adulte | H20: 06 86 14 57 57 | I20: TRUE | J20: FALSE | K20: FALSE | L20: FALSE | M20: TRUE | N20: TRUE | O20: TRUE | P20: TRUE | Q20: TRUE | R20: FALSE | S20: TRUE | T20: FALSE | U20: FALSE | V20: FALSE | W20: Femme de de regis G
A21: En cours | B21: GINTZ | C21: Vincent | D21: Famille Léa | E21: Adulte | F21: 6 rue de la forge 67370 behlenheim | H21: 06 12 51 56 99 | I21: TRUE | J21: TRUE | K21: FALSE | L21: FALSE | M21: TRUE | N21: TRUE | O21: TRUE | P21: TRUE | Q21: TRUE | R21: TRUE | S21: TRUE | T21: FALSE | U21: FALSE | V21: FALSE | W21: Oncle de lea du coté de son pere
A22: En cours | B22: GINTZ | C22: Joëlle | D22: Famille Léa | E22: Adulte | I22: TRUE | J22: FALSE | K22: FALSE | L22: FALSE | M22: TRUE | N22: TRUE | O22: TRUE | P22: TRUE | Q22: TRUE | R22: FALSE | S22: TRUE | T22: FALSE | U22: FALSE | V22: FALSE | W22: Femme de Vincent G
A23: En cours | B23: KIEFFER | C23: Jean-Marc | D23: Famille Léa | E23: Adulte | F23: 10 rue des Roses, 67370 Behlenheim-Truchtersheim | I23: TRUE | J23: TRUE | K23: FALSE | L23: FALSE | M23: TRUE | N23: TRUE | O23: TRUE | P23: TRUE | Q23: TRUE | R23: TRUE | S23: TRUE | T23: FALSE | U23: FALSE | V23: FALSE | W23: ami du père de lea
A24: En cours | B24: KIEFFER | C24: Marie | D24: Famille Léa | E24: Adulte | H24: 06 64 16 62 06 | I24: TRUE | J24: FALSE | K24: FALSE | L24: FALSE | M24: TRUE | N24: TRUE | O24: TRUE | P24: TRUE | Q24: TRUE | R24: TRUE | S24: TRUE | T24: FALSE | U24: FALSE | V24: FALSE | W24: Femme de JM Kieffer
A25: En cours | B25: MEYER | C25: Jeanne | D25: Famille Léa | E25: Adulte | H25: 06 29 09 36 12 | I25: TRUE | J25: TRUE | K25: FALSE | L25: FALSE | M25: FALSE | N25: FALSE | O25: FALSE | P25: FALSE | Q25: FALSE | R25: FALSE | S25: FALSE | T25: FALSE | U25: FALSE | V25: FALSE | W25: Soeur de la grand mere de Léa Chrisitnane G
A26: En cours | B26: MEYER | C26: Gilbert | D26: Famille Léa | E26: Adulte | I26: TRUE | J26: FALSE | K26: FALSE | L26: FALSE | M26: FALSE | N26: FALSE | O26: FALSE | P26: FALSE | Q26: FALSE | R26: FALSE | S26: FALSE | T26: FALSE | U26: FALSE | V26: FALSE | W26: Mari de Jeanne MEYER
A27: Traité | B27: GIANNIKAS | C27: Leonidas | D27: Amis Léa | E27: Adulte | H27: 06 50 66 07 59 | I27: TRUE | J27: FALSE | K27: TRUE | L27: TRUE | M27: TRUE | N27: TRUE | O27: TRUE | P27: TRUE | Q27: TRUE | R27: TRUE | S27: TRUE | T27: TRUE | U27: FALSE | V27: FALSE | W27: Meilleur ami de Romain G
A28: En cours | B28: CLAUDON | C28: Clémence | D28: Amis Léa | E28: Adulte | H28: 06 51 89 01 85 | I28: TRUE | J28: FALSE | K28: FALSE | L28: FALSE | M28: TRUE | N28: TRUE | O28: TRUE | P28: TRUE | Q28: TRUE | R28: TRUE | S28: TRUE | T28: FALSE | U28: FALSE | V28: FALSE | W28: Amie de Lea
A29: En cours | B29: NEITER | C29: Loanne | D29: Amis Léa | E29: Adulte | H29: 06 87 47 87 68 | I29: TRUE | J29: TRUE | K29: TRUE | L29: TRUE | M29: TRUE | N29: TRUE | O29: TRUE | P29: TRUE | Q29: TRUE | R29: TRUE | S29: TRUE | T29: TRUE | U29: FALSE | V29: TRUE | W29: Amie de Lea
A30: En cours | C30: Armand | D30: Amis Léa | E30: Adulte | H30: 07 82 24 14 29 | I30: TRUE | J30: FALSE | K30: TRUE | L30: TRUE | M30: TRUE | N30: TRUE | O30: TRUE | P30: TRUE | Q30: TRUE | R30: TRUE | S30: TRUE | T30: TRUE | U30: FALSE | V30: FALSE | W30: Copain de Loanne Neiter
A31: En cours | B31: RASANAYAGAM | C31: Marjorie | D31: Amis Léa | E31: Adulte | H31: 06 58 21 24 63 | I31: TRUE | J31: TRUE | K31: TRUE | L31: TRUE | M31: TRUE | N31: TRUE | O31: TRUE | P31: TRUE | Q31: TRUE | R31: TRUE | S31: TRUE | T31: TRUE | U31: FALSE | V31: TRUE | W31: Amie de Lea
A32: En cours | B32: GRISEVIC | C32: Leya | D32: Amis Léa | E32: Adulte | H32: 06 95 28 35 29 | I32: TRUE | J32: TRUE | K32: TRUE | L32: TRUE | M32: TRUE | N32: TRUE | O32: TRUE | P32: TRUE | Q32: TRUE | R32: TRUE | S32: TRUE | T32: TRUE | U32: FALSE | V32: TRUE | W32: Amie de Lea
A33: En cours | B33: KAYEMBE | C33: Audrey | D33: Amis Léa | E33: Adulte | H33: 06 60 48 09 19 | I33: TRUE | J33: FALSE | K33: FALSE | L33: FALSE | M33: FALSE | N33: TRUE | O33: TRUE | P33: TRUE | Q33: TRUE | R33: TRUE | S33: TRUE | T33: FALSE | U33: FALSE | V33: FALSE | W33: Amie de Lea
A34: En cours | B34: ANGOT | C34: Gabrielle | D34: Amis Léa | E34: Adulte | G34: gabrielle.angot@gmail.com | H34: 06 23 67 42 40 | I34: TRUE | J34: FALSE | K34: FALSE | L34: FALSE | M34: FALSE | N34: TRUE | O34: TRUE | P34: TRUE | Q34: TRUE | R34: TRUE | S34: TRUE | T34: FALSE | U34: FALSE | V34: FALSE | W34: Amie de Lea
A35: En cours | B35: BERTRAND | C35: Louise | D35: Amis Léa | E35: Adulte | G35: louisebertrand123@gmail.com | H35: 06 51 44 69 10 | I35: TRUE | J35: TRUE | K35: TRUE | L35: TRUE | M35: TRUE | N35: TRUE | O35: TRUE | P35: TRUE | Q35: TRUE | R35: TRUE | S35: TRUE | T35: TRUE | U35: FALSE | V35: TRUE | W35: Amie de Lea
A36: En cours | B36: AMBARTSONOVA | C36: Naza | D36: Amis Léa | E36: Adulte | G36: naza31072001@gmail.com | H36: 06 95 03 50 64 | I36: TRUE | J36: FALSE | K36: FALSE | L36: FALSE | M36: FALSE | N36: TRUE | O36: TRUE | P36: TRUE | Q36: TRUE | R36: FALSE | S36: TRUE | T36: FALSE | U36: FALSE | V36: FALSE | W36: Amie de Lea
A37: En cours | B37: COUBARD | C37: Christophe | D37: Famille PA | E37: Adulte | F37: 20 Rue Du Docteur Touchard 72140 Sillé Le Guillaume France | I37: TRUE | J37: TRUE | K37: TRUE | L37: TRUE | M37: TRUE | N37: TRUE | O37: TRUE | P37: TRUE | Q37: TRUE | R37: TRUE | S37: TRUE | T37: TRUE | U37: FALSE | V37: FALSE | W37: Pere de PA
A38: En cours | B38: MAGALHAES | C38: Luis | D38: Famille PA | E38: Adulte | I38: TRUE | J38: FALSE | K38: TRUE | L38: TRUE | M38: TRUE | N38: TRUE | O38: TRUE | P38: TRUE | Q38: TRUE | R38: TRUE | S38: TRUE | T38: TRUE | U38: FALSE | V38: FALSE | W38: Mari de Chrisitphe C et beau-père de PA
A39: En cours | B39: COUBARD | C39: Constance | D39: Famille PA | E39: Adulte | F39: 12 Rue de l’Université de Chicago 97300 CAYENNE | I39: TRUE | J39: TRUE | K39: TRUE | L39: TRUE | M39: TRUE | N39: TRUE | O39: TRUE | P39: TRUE | Q39: TRUE | R39: TRUE | S39: TRUE | T39: TRUE | U39: FALSE | V39: FALSE | W39: Mere de PA
A40: En cours | B40: LORENTE | C40: Hugues | D40: Famille PA | E40: Adulte | I40: TRUE | J40: FALSE | K40: TRUE | L40: TRUE | M40: TRUE | N40: TRUE | O40: TRUE | P40: TRUE | Q40: TRUE | R40: TRUE | S40: TRUE | T40: TRUE | U40: FALSE | V40: FALSE | W40: Mari de Constance C et beau père de PA
A41: En cours | B41: COUBARD | C41: Séverine | D41: Famille PA | E41: Adulte | F41: 1 Rue de Castelnau 68000 Colmar France | I41: TRUE | J41: TRUE | K41: TRUE | L41: TRUE | M41: TRUE | N41: TRUE | O41: TRUE | P41: TRUE | Q41: TRUE | R41: FALSE | S41: TRUE | T41: TRUE | U41: FALSE | V41: TRUE | W41: Soeur de PA
A42: En cours | B42: BOOLUCK | C42: Paul | D42: Famille PA | E42: Adulte | I42: TRUE | J42: FALSE | K42: TRUE | L42: TRUE | M42: TRUE | N42: TRUE | O42: TRUE | P42: TRUE | Q42: TRUE | R42: TRUE | S42: TRUE | T42: TRUE | U42: FALSE | V42: FALSE | W42: Mari de Severine C
A43: En cours | B43: COUBARD | C43: Maximilien | D43: Famille PA | E43: Adulte | F43: 1 Square Padirac 75016 Paris France | I43: TRUE | J43: TRUE | K43: TRUE | L43: TRUE | M43: TRUE | N43: TRUE | O43: TRUE | P43: TRUE | Q43: TRUE | R43: TRUE | S43: TRUE | T43: TRUE | U43: FALSE | V43: TRUE | W43: Frere de PA
A44: Non traité | B44: HADJAR | C44: Isack | D44: Famille PA | E44: Adulte | I44: TRUE | J44: FALSE | K44: FALSE | L44: FALSE | M44: FALSE | N44: FALSE | O44: FALSE | P44: FALSE | Q44: FALSE | R44: FALSE | S44: FALSE | T44: FALSE | U44: FALSE | V44: FALSE | W44: Meilleur ami de MAximielin C
A45: En cours | B45: VAILLANT | C45: Marie-France | D45: Famille PA | E45: Adulte | F45: 9 impasse de l ouillette 85200 Fontenay Le Comte France | I45: TRUE | J45: TRUE | K45: TRUE | L45: TRUE | M45: TRUE | N45: TRUE | O45: TRUE | P45: TRUE | Q45: TRUE | R45: FALSE | S45: TRUE | T45: TRUE | U45: FALSE | V45: FALSE | W45: Grand mere paternel PA
A46: En cours | B46: RAISON | C46: Alain | D46: Famille PA | E46: Adulte | I46: TRUE | J46: FALSE | K46: TRUE | L46: TRUE | M46: TRUE | N46: TRUE | O46: TRUE | P46: TRUE | Q46: TRUE | R46: FALSE | S46: TRUE | T46: TRUE | U46: FALSE | V46: FALSE | W46: Conjoint de Marie FRance V
A47: Non traité | B47: MESLIN | C47: Valérie | D47: Famille PA | E47: Adulte | I47: TRUE | J47: FALSE | K47: FALSE | L47: TRUE | M47: TRUE | N47: TRUE | O47: TRUE | P47: TRUE | Q47: TRUE | R47: TRUE | S47: TRUE | T47: FALSE | U47: FALSE | V47: FALSE | W47: Tante et marinaen de PA
A48: Non traité | B48: MESLIN | C48: Thierry | D48: Famille PA | E48: Adulte | I48: TRUE | J48: FALSE | K48: FALSE | L48: TRUE | M48: TRUE | N48: TRUE | O48: TRUE | P48: TRUE | Q48: TRUE | R48: TRUE | S48: TRUE | T48: FALSE | U48: FALSE | V48: FALSE | W48: Marie de tata valeire
A49: Non traité | B49: MESLIN | C49: Antoine | D49: Famille PA | E49: Adulte | I49: TRUE | J49: FALSE | K49: FALSE | L49: TRUE | M49: TRUE | N49: TRUE | O49: TRUE | P49: TRUE | Q49: TRUE | R49: TRUE | S49: TRUE | T49: FALSE | U49: FALSE | V49: FALSE | W49: Cousin de PA
A50: Non traité | C50: Marion | D50: Famille PA | E50: Adulte | I50: TRUE | J50: FALSE | K50: FALSE | L50: TRUE | M50: TRUE | N50: TRUE | O50: TRUE | P50: TRUE | Q50: TRUE | R50: TRUE | S50: TRUE | T50: FALSE | U50: FALSE | V50: FALSE | W50: Copine d’antoine Meslin
A51: Non traité | B51: MESLIN | C51: Adrien | D51: Famille PA | E51: Adulte | I51: TRUE | J51: FALSE | K51: FALSE | L51: TRUE | M51: TRUE | N51: TRUE | O51: TRUE | P51: TRUE | Q51: TRUE | R51: TRUE | S51: TRUE | T51: FALSE | U51: FALSE | V51: FALSE | W51: Cousin de PA
A52: Non traité | C52: Noémie | D52: Famille PA | E52: Adulte | I52: TRUE | J52: FALSE | K52: FALSE | L52: TRUE | M52: TRUE | N52: TRUE | O52: TRUE | P52: TRUE | Q52: TRUE | R52: TRUE | S52: TRUE | T52: FALSE | U52: FALSE | V52: FALSE | W52: Copine d’adrien MEslin
A53: Non traité | B53: COUBARD | C53: Malaurie | D53: Famille PA | E53: Adulte | I53: TRUE | J53: FALSE | K53: FALSE | L53: FALSE | M53: FALSE | N53: TRUE | O53: TRUE | P53: TRUE | Q53: TRUE | R53: TRUE | S53: TRUE | T53: FALSE | U53: FALSE | V53: FALSE | W53: Cousine de PA
A54: Non traité | C54: Adrien | D54: Famille PA | E54: Adulte | I54: TRUE | J54: FALSE | K54: FALSE | L54: FALSE | M54: FALSE | N54: TRUE | O54: TRUE | P54: TRUE | Q54: TRUE | R54: TRUE | S54: TRUE | T54: FALSE | U54: FALSE | V54: FALSE | W54: Copain de Malaurie C
A55: Non traité | B55: COUBARD | C55: Stéphane | D55: Famille PA | E55: Adulte | I55: TRUE | J55: FALSE | K55: FALSE | L55: FALSE | M55: FALSE | N55: TRUE | O55: TRUE | P55: TRUE | Q55: TRUE | R55: TRUE | S55: TRUE | T55: FALSE | U55: FALSE | V55: FALSE | W55: Oncle paternel de PA
A56: Non traité | C56: Sandrine | D56: Famille PA | E56: Adulte | I56: TRUE | J56: FALSE | K56: FALSE | L56: FALSE | M56: FALSE | N56: TRUE | O56: TRUE | P56: TRUE | Q56: TRUE | R56: TRUE | S56: TRUE | T56: FALSE | U56: FALSE | V56: FALSE | W56: Copien de Stephane Coubard
A57: En cours | B57: JANSSENS | C57: Cacotte | D57: Famille PA | E57: Adulte | I57: TRUE | J57: FALSE | K57: TRUE | L57: TRUE | M57: TRUE | N57: TRUE | O57: TRUE | P57: TRUE | Q57: TRUE | R57: FALSE | S57: TRUE | T57: TRUE | U57: FALSE | V57: FALSE | W57: Meilleur amis de Christophe C
A58: En cours | B58: JANSSENS | C58: Marco | D58: Famille PA | E58: Adulte | I58: TRUE | J58: FALSE | K58: TRUE | L58: TRUE | M58: TRUE | N58: TRUE | O58: TRUE | P58: TRUE | Q58: TRUE | R58: TRUE | S58: TRUE | T58: TRUE | U58: FALSE | V58: FALSE | W58: Mari de Cacotte
A59: En cours | B59: MENSAH | C59: Théo | D59: Famille PA | E59: Adulte | F59: 48 rue salvador allende 92000 Nanterre France | I59: TRUE | J59: TRUE | K59: TRUE | L59: TRUE | M59: TRUE | N59: TRUE | O59: TRUE | P59: TRUE | Q59: TRUE | R59: TRUE | S59: TRUE | T59: FALSE | U59: FALSE | V59: TRUE | W59: Oncle maternel de PA
A60: Non traité | B60: MENSAH | C60: Claude | D60: Famille PA | E60: Adulte | I60: TRUE | J60: FALSE | K60: FALSE | L60: TRUE | M60: TRUE | N60: TRUE | O60: TRUE | P60: TRUE | Q60: TRUE | R60: TRUE | S60: TRUE | T60: FALSE | U60: FALSE | V60: FALSE | W60: Oncle maternel de PA
A61: Non traité | B61: MENSAH | C61: Mickael | D61: Famille PA | E61: Adulte | I61: TRUE | J61: FALSE | K61: FALSE | L61: TRUE | M61: TRUE | N61: TRUE | O61: TRUE | P61: TRUE | Q61: TRUE | R61: TRUE | S61: TRUE | T61: FALSE | U61: FALSE | V61: FALSE | W61: Oncle maternel de PA
A62: Non traité | B62: MENSAH | C62: Guy | D62: Famille PA | E62: Adulte | I62: TRUE | J62: FALSE | K62: FALSE | L62: TRUE | M62: TRUE | N62: TRUE | O62: TRUE | P62: TRUE | Q62: TRUE | R62: TRUE | S62: TRUE | T62: FALSE | U62: FALSE | V62: FALSE | W62: Oncle maternel de PA
A63: En cours | B63: MENSAH | C63: Maéva | D63: Famille PA | E63: Adulte | I63: TRUE | J63: FALSE | K63: TRUE | L63: TRUE | M63: TRUE | N63: TRUE | O63: TRUE | P63: TRUE | Q63: TRUE | R63: TRUE | S63: TRUE | T63: FALSE | U63: FALSE | V63: FALSE | W63: Cousine maternele de PA
A64: En cours | B64: MENSAH | C64: Giresse | D64: Famille PA | E64: Adulte | I64: TRUE | J64: FALSE | K64: TRUE | L64: TRUE | M64: TRUE | N64: TRUE | O64: TRUE | P64: TRUE | Q64: TRUE | R64: TRUE | S64: TRUE | T64: FALSE | U64: FALSE | V64: FALSE | W64: Cousine maternele de PA
A65: En cours | C65: Marjorie | D65: Famille PA | E65: Adulte | I65: TRUE | J65: FALSE | K65: TRUE | L65: TRUE | M65: TRUE | N65: TRUE | O65: TRUE | P65: TRUE | Q65: TRUE | R65: TRUE | S65: TRUE | T65: FALSE | U65: FALSE | V65: FALSE | W65: Copien de Giresse
A66: En cours | B66: MENSAH | C66: Pauline | D66: Famille PA | E66: Adulte | I66: TRUE | J66: FALSE | K66: TRUE | L66: TRUE | M66: TRUE | N66: TRUE | O66: TRUE | P66: TRUE | Q66: TRUE | R66: FALSE | S66: TRUE | T66: TRUE | U66: FALSE | V66: FALSE | W66: Grand mere maternelle de PA
A67: En cours | B67: LORENTE | C67: Gisèle | D67: Famille PA | E67: Adulte | I67: TRUE | J67: TRUE | K67: FALSE | L67: FALSE | M67: FALSE | N67: FALSE | O67: FALSE | P67: FALSE | Q67: FALSE | R67: FALSE | S67: FALSE | T67: FALSE | U67: FALSE | V67: FALSE | W67: Mère de Hugues, considère comme grande mere de PA
A68: En cours | B68: LORENTE | C68: Salvador | D68: Famille PA | E68: Adulte | I68: TRUE | J68: FALSE | K68: FALSE | L68: FALSE | M68: FALSE | N68: FALSE | O68: FALSE | P68: FALSE | Q68: FALSE | R68: FALSE | S68: FALSE | T68: FALSE | U68: FALSE | V68: FALSE | W68: Mari de Gislee
A69: Non traité | B69: LORENTE | C69: Clément | D69: Famille PA | E69: Adulte | I69: TRUE | J69: FALSE | K69: FALSE | L69: FALSE | M69: FALSE | N69: FALSE | O69: FALSE | P69: FALSE | Q69: FALSE | R69: FALSE | S69: FALSE | T69: FALSE | U69: FALSE | V69: FALSE | W69: Fils de Hugues, demi frère mais pas de sang de PA
A70: Non traité | B70: LORENTE | C70: Charles | D70: Famille PA | E70: Adulte | I70: TRUE | J70: FALSE | K70: FALSE | L70: FALSE | M70: FALSE | N70: FALSE | O70: FALSE | P70: FALSE | Q70: FALSE | R70: FALSE | S70: FALSE | T70: FALSE | U70: FALSE | V70: FALSE | W70: Fils de Hugues, demi frère mais pas de sang de PA
A71: Non traité | B71: OSSÉ | C71: Céline | D71: Famille PA | E71: Adulte | I71: TRUE | J71: TRUE | K71: FALSE | L71: TRUE | M71: TRUE | N71: TRUE | O71: TRUE | P71: TRUE | Q71: TRUE | R71: FALSE | S71: TRUE | T71: TRUE | U71: FALSE | V71: FALSE | W71: Meilleure amie de Constance C
A72: Non traité | B72: OSSÉ | C72: Pascale | D72: Famille PA | E72: Adulte | I72: TRUE | J72: FALSE | K72: FALSE | L72: FALSE | M72: FALSE | N72: FALSE | O72: FALSE | P72: FALSE | Q72: FALSE | R72: FALSE | S72: FALSE | T72: FALSE | U72: FALSE | V72: FALSE | W72: Fille de Céline Ossé
A73: Non traité | B73: OSSÉ | C73: Stéphanie | D73: Famille PA | E73: Adulte | I73: TRUE | J73: FALSE | K73: FALSE | L73: FALSE | M73: FALSE | N73: FALSE | O73: FALSE | P73: FALSE | Q73: FALSE | R73: FALSE | S73: FALSE | T73: FALSE | U73: FALSE | V73: FALSE | W73: Fille de Céline Ossé
A74: Non traité | B74: OSSÉ | C74: Sidney | D74: Famille PA | E74: Adulte | I74: TRUE | J74: FALSE | K74: FALSE | L74: FALSE | M74: FALSE | N74: FALSE | O74: FALSE | P74: FALSE | Q74: FALSE | R74: FALSE | S74: FALSE | T74: FALSE | U74: FALSE | V74: FALSE | W74: Fils de Céline Ossé
A75: En cours | B75: HARO | C75: Alexandre | D75: Amis PA | E75: Adulte | I75: TRUE | J75: TRUE | K75: TRUE | L75: TRUE | M75: TRUE | N75: TRUE | O75: TRUE | P75: TRUE | Q75: TRUE | R75: TRUE | S75: TRUE | T75: TRUE | U75: FALSE | V75: TRUE | W75: Meilleur Ami PA
A76: En cours | B76: DOUMEN | C76: Yoann | D76: Amis PA | E76: Adulte | I76: TRUE | J76: TRUE | K76: TRUE | L76: TRUE | M76: TRUE | N76: TRUE | O76: TRUE | P76: TRUE | Q76: TRUE | R76: TRUE | S76: TRUE | T76: TRUE | U76: FALSE | V76: TRUE | W76: Meilleur Ami PA
A77: En cours | B77: VUILLEMIN | C77: Laure | D77: Amis PA | E77: Adulte | I77: TRUE | J77: FALSE | K77: TRUE | L77: TRUE | M77: TRUE | N77: TRUE | O77: TRUE | P77: TRUE | Q77: TRUE | R77: TRUE | S77: TRUE | T77: TRUE | U77: TRUE | V77: FALSE | W77: Copine de Yoann doumen
A78: Non traité | B78: BAUDIMANT | C78: Goulven | D78: Amis PA | E78: Adulte | I78: TRUE | J78: FALSE | K78: FALSE | L78: FALSE | M78: FALSE | N78: TRUE | O78: TRUE | P78: TRUE | Q78: TRUE | R78: TRUE | S78: TRUE | T78: FALSE | U78: FALSE | V78: FALSE | W78: Meilleur Ami PA
A79: Non traité | C79: Léa | D79: Amis PA | E79: Adulte | I79: TRUE | J79: FALSE | K79: FALSE | L79: FALSE | M79: FALSE | N79: TRUE | O79: TRUE | P79: TRUE | Q79: TRUE | R79: TRUE | S79: TRUE | T79: FALSE | U79: FALSE | V79: FALSE | W79: Copine de Gouvlen
A80: En cours | B80: BAKTHA | C80: Bilel | D80: Amis PA | E80: Adulte | I80: TRUE | J80: TRUE | K80: TRUE | L80: TRUE | M80: TRUE | N80: TRUE | O80: TRUE | P80: TRUE | Q80: TRUE | R80: TRUE | S80: TRUE | T80: TRUE | U80: FALSE | V80: TRUE | W80: Meilleur Ami PA
A81: En cours | C81: Lucile | D81: Amis PA | E81: Adulte | I81: TRUE | J81: FALSE | K81: FALSE | L81: TRUE | M81: TRUE | N81: TRUE | O81: TRUE | P81: TRUE | Q81: TRUE | R81: TRUE | S81: TRUE | T81: TRUE | U81: FALSE | V81: FALSE | W81: Copien de Bilel
A82: En cours | B82: AUBERT | C82: Olivier | D82: Amis PA | E82: Adulte | I82: TRUE | J82: TRUE | K82: TRUE | L82: FALSE | M82: FALSE | N82: TRUE | O82: TRUE | P82: TRUE | Q82: TRUE | R82: TRUE | S82: TRUE | T82: FALSE | U82: FALSE | V82: FALSE | W82: Ami PA
A83: En cours | B83: DIOUNOU | C83: Jordan | D83: Amis PA | E83: Adulte | I83: TRUE | J83: TRUE | K83: TRUE | L83: FALSE | M83: FALSE | N83: TRUE | O83: TRUE | P83: TRUE | Q83: TRUE | R83: TRUE | S83: TRUE | T83: FALSE | U83: FALSE | V83: FALSE | W83: Ami PA
A84: En cours | B84: SAO-CORDIEZ | C84: Aimé | D84: Amis PA | E84: Adulte | I84: TRUE | J84: FALSE | K84: FALSE | L84: FALSE | M84: FALSE | N84: TRUE | O84: TRUE | P84: TRUE | Q84: TRUE | R84: TRUE | S84: TRUE | T84: FALSE | U84: FALSE | V84: FALSE | W84: Ami PA
A85: En cours | B85: JAUERNIG | C85: Luke | D85: Amis PA | E85: Adulte | I85: TRUE | J85: TRUE | K85: TRUE | L85: FALSE | M85: FALSE | N85: TRUE | O85: TRUE | P85: TRUE | Q85: TRUE | R85: TRUE | S85: TRUE | T85: FALSE | U85: FALSE | V85: FALSE | W85: Ami PA
A86: En cours | B86: GAMBUT | C86: Elliot | D86: Amis PA | E86: Adulte | I86: TRUE | J86: FALSE | K86: TRUE | L86: FALSE | M86: FALSE | N86: TRUE | O86: TRUE | P86: TRUE | Q86: TRUE | R86: TRUE | S86: TRUE | T86: FALSE | U86: FALSE | V86: FALSE | W86: Ami PA
A87: En cours | C87: Alina | D87: Amis PA | E87: Adulte | I87: TRUE | J87: FALSE | K87: TRUE | L87: FALSE | M87: FALSE | N87: TRUE | O87: TRUE | P87: TRUE | Q87: TRUE | R87: TRUE | S87: TRUE | T87: FALSE | U87: FALSE | V87: FALSE | W87: Copine d’Elliot G
A88: En cours | B88: VIEYRA | C88: Charles | D88: Amis PA | E88: Adulte | I88: TRUE | J88: FALSE | K88: TRUE | L88: FALSE | M88: FALSE | N88: TRUE | O88: TRUE | P88: TRUE | Q88: TRUE | R88: TRUE | S88: TRUE | T88: FALSE | U88: FALSE | V88: FALSE | W88: Ami PA
A89: Non traité | B89: GLAUDE | C89: Jonathan | D89: Amis PA | E89: Adulte | I89: TRUE | J89: FALSE | K89: FALSE | L89: FALSE | M89: FALSE | N89: FALSE | O89: FALSE | P89: FALSE | Q89: FALSE | R89: FALSE | S89: FALSE | T89: FALSE | U89: FALSE | V89: FALSE | W89: Ami PA
A90: Non traité | B90: GLAUDE | C90: Jacqueline | D90: Amis PA | E90: Adulte | I90: TRUE | J90: FALSE | K90: FALSE | L90: FALSE | M90: FALSE | N90: FALSE | O90: FALSE | P90: FALSE | Q90: FALSE | R90: FALSE | S90: FALSE | T90: FALSE | U90: FALSE | V90: FALSE | W90: Femme de Jonathan Glaude
B91: {=COUNTA($C2:$C90)} -> 89 | I91: {=COUNTIF(I4:I90,TRUE)+2} -> 89 | J91: {=COUNTIF(J4:J90,TRUE)+2} -> 30 | K91: {=COUNTIF(K4:K90,TRUE)+2} -> 44 | L91: {=COUNTIF(L4:L90,TRUE)+2} -> 49 | M91: {=COUNTIF(M4:M90,TRUE)+2} -> 58 | N91: {=COUNTIF(N4:N90,TRUE)+2} -> 74 | O91: {=COUNTIF(O4:O90,TRUE)+2} -> 74 | P91: {=COUNTIF(P4:P90,TRUE)+2} -> 74 | ... T91: {=COUNTIF(T4:T90,TRUE)+2} -> 36 | U91: {=COUNTIF(U4:U90,TRUE)} -> 1 | V91: {=COUNTIF(V4:V90,TRUE)} -> 12

Sheet Témoins & Honneurs - Tableau 1
A1: Témoins | B1: Église | C1: Mairie
A2: Léa
A3: 1 | B3: Amélie | C3: Amélie
A4: 2 | B4: Romain | C4: Romain
A5: PA
A6: 1 | B6: Séverine | C6: Séverine
A7: 2 | B7: Maximilien | C7: Maximilien

Sheet Témoins & Honneurs - Tableau 1-
A1: Honneurs | B1: Nom | C1: Rôle
A2: Léa
A3: 1 | B3: Séverine
A4: 2 | B4: Amélie
A5: 3 | B5: Marjorie
A6: 4 | B6: Loanne
A7: 5 | B7: Louise | C7: EVJF
A8: 6 | B8: Leya
A9: PA
A10: 1 | B10: Alexandre | C10: EVG
A11: 2 | B11: Yoann | C11: Costume
A12: 3 | B12: Bilel
A13: 4 | B13: Luke
A14: 5 | B14: Maximilien
A15: 6 | B15: Tonton Théo

Sheet EVJF & EVG - Léa
A1: Léa
A2: Liste
A3: Léa
A4: Marjorie
A5: Louise
A6: Loanne
A7: Leya
A8: Amelie
A9: Severine
A10: Audrey
A11: Gabrielle
A12: Naza
... A14: Melissande

Sheet EVJF & EVG - PA
A1: PA
A2: Liste
A3: PA
A4: Alexandre
A5: Bilel
A6: Yoann
A7: Luke
A8: Olivier
A9: Jordan
A10: Goulven

Sheet Lieu
B2: Nom | C2: Prise de contact ? | D2: Retour ? | E2: Ok ? | F2: Pref Léa | G2: Lien | H2: Adresse | I2: Distance Paris | J2: Distance Paris | K2: Prix location | L2: Prix logements | M2: Total | N2: Nb jours de location | O2: Infos | P2: Traiteur imposé ? | Q2: Eglise dans le domaine | R2: Nombre d’invités (debout) | S2: Nombre d’invités (assis) | T2: Nombre de chambre | U2: Nombre de couchages | V2: Piscine | W2: Notes | X2: A visiter
B3: Domaine de Guerquesalle | C3: TRUE | D3: TRUE | E3: TRUE | F3: TRUE | G3: https://www.mariages.net/domaine-mariage/domaine-de-guerquesalle--e143600 | H3: Ferme de Guerquesalle 27140 Amécourt (Eure) | I3: 1h15 | J3: 1.25 | K3: 6400 | L3: 3500 | M3: {=_xlfn.IFERROR(K3+L3,50000)} -> 9900 | N3: 3 | O3: du vendredi 17h au dimanche 17h | P3: Non | Q3: Non | R3: 300 | S3: 220 | T3: 16 | U3: 40 | V3: Non | W3: {=IF(J3<2.1,1,0)+IF(M3<'Budget - Budget'!$C$3,2,0)+IF(S3<'Invités'!$B$91,0,1)+IF(U3>'Invités'!$P$91,2,0)+IF(V3="Non",0,1)+IF(Q3="Oui",1,0)+IF(P3="Non",2,0)+IF(N3>2,2,0)+IF(M3>15000,-2,0)} -> 8 | X3: TRUE
B4: Domaine de Meaucé | C4: TRUE | D4: TRUE | E4: TRUE | F4: TRUE | G4: https://www.mariages.net/domaine-mariage/domaine-de-meauce--e168716 | H4: La Grand' Maison 28240 Meaucé (Eure-et-Loir) | I4: 1h50 | J4: 1.83 | K4: 10800 | L4: 3000 | M4: {=_xlfn.IFERROR(K4+L4,50000)+((0.9*2)*'Invités'!P$91)} -> 13933.2 | N4: 3 | O4: vendredi midi au dimanche 18h | P4: Oui | Q4: Non | R4: 150 | S4: 150 | T4: 31 | U4: 86 | V4: Oui | W4: {=IF(J4<2.1,1,0)+IF(M4<'Budget - Budget'!$C$3,2,0)+IF(S4<'Invités'!$B$91,0,1)+IF(U4>'Invités'!$P$91,2,0)+IF(V4="Non",0,1)+IF(Q4="Oui",1,0)+IF(P4="Non",2,0)+IF(N4>2,2,0)+IF(M4>15000,-2,0)} -> 9 | X4: TRUE
B5: Domaine des Libellules | C5: TRUE | D5: TRUE | E5: TRUE | F5: FALSE | G5: https://www.mariages.net/domaine-mariage/domaine-des-libellules--e386935 | H5: Domaine des Libellules - La Chaise 28800 Bonneval (Eure-et-Loir) | I5: 2h | J5: 2 | K5: {=7800+420} -> 8220 | L5: 7848 | M5: {=_xlfn.IFERROR(K5+L5,50000)} -> 16068 | N5: 3 | O5: Vendredi 11h00 au dimanche 17h00 | P5: Non | Q5: Non | R5: 150 | S5: 150 | T5: 23 | U5: 68 | V5: Oui | W5: {=IF(J5<2.1,1,0)+IF(M5<'Budget - Budget'!$C$3,2,0)+IF(S5<'Invités'!$B$91,0,1)+IF(U5>'Invités'!$P$91,2,0)+IF(V5="Non",0,1)+IF(Q5="Oui",1,0)+IF(P5="Non",2,0)+IF(N5>2,2,0)+IF(M5>15000,-2,0)} -> 7 | X5: TRUE
B6: Le Saint Leonard | C6: TRUE | D6: TRUE | E6: TRUE | F6: FALSE | G6: https://www.mariages.net/domaine-mariage/le-saint-leonard--e358295 | H6: 4, Impasse du Prieure 77151 Montceaux-lès-Provins (Seine-et-Marne) | I6: 2h | J6: 2 | K6: 5400 | L6: 700 | M6: {=_xlfn.IFERROR(K6+L6,50000)} -> 6100 | N6: 3 | O6: vendredi après midi au dimanche 17h | P6: Non | Q6: Oui | R6: 250 | S6: 250 | T6: 8 | U6: 25 | V6: Non | W6: {=IF(J6<2.1,1,0)+IF(M6<'Budget - Budget'!$C$3,2,0)+IF(S6<'Invités'!$B$91,0,1)+IF(U6>'Invités'!$P$91,2,0)+IF(V6="Non",0,1)+IF(Q6="Oui",1,0)+IF(P6="Non",2,0)+IF(N6>2,2,0)+IF(M6>15000,-2,0)} -> 9 | X6: FALSE
B7: Vaumonteuil | C7: TRUE | D7: TRUE | E7: TRUE | F7: TRUE | G7: https://www.mariages.net/domaine-mariage/vaumonteuil--e247147 | H7: 14, Rue du Pont Kennedy 28240 Belhomert-Guéhouville (Eure-et-Loir) | I7: 1h45 | J7: 1.75 | K7: 7900 | L7: 0 | M7: {=_xlfn.IFERROR(K7+L7,50000)} -> 7900 | N7: 3 | O7: du vendredi 14h au dimanche 17h | P7: Non | Q7: Non | R7: 180 | S7: 180 | T7: 12 | U7: 27 | V7: Oui | W7: {=IF(J7<2.1,1,0)+IF(M7<'Budget - Budget'!$C$3,2,0)+IF(S7<'Invités'!$B$91,0,1)+IF(U7>'Invités'!$P$91,2,0)+IF(V7="Non",0,1)+IF(Q7="Oui",1,0)+IF(P7="Non",2,0)+IF(N7>2,2,0)+IF(M7>15000,-2,0)} -> 9 | X7: FALSE
B8: Domaine des Bayettes | C8: TRUE | D8: TRUE | E8: FALSE | G8: https://www.mariages.net/domaine-mariage/domaine-des-bayettes--e303720 | H8: 10, Route Nationale 78980 Mondreville (Yvelines) | I8: 1h | J8: 1 | K8: 9900 | L8: 0 | M8: {=_xlfn.IFERROR(K8+L8,50000)} -> 9900 | N8: 3 | O8: du vendredi 15h00 au dimanche 17h00 | P8: Non | Q8: Non | R8: 150 | S8: 150 | T8: 6 | U8: 22 | V8: Oui | W8: {=IF(J8<2.1,1,0)+IF(M8<'Budget - Budget'!$C$3,2,0)+IF(S8<'Invités'!$B$91,0,1)+IF(U8>'Invités'!$P$91,2,0)+IF(V8="Non",0,1)+IF(Q8="Oui",1,0)+IF(P8="Non",2,0)+IF(N8>2,2,0)+IF(M8>15000,-2,0)} -> 9 | X8: FALSE
B9: La Grange des Triplés | C9: TRUE | D9: TRUE | E9: TRUE | F9: FALSE | G9: https://www.mariages.net/domaine-mariage/la-grange-des-triples--e148536 | H9: 67, Route des Andelys 27150 Boisemont (Eure) | I9: 1h15 | J9: 1.25 | K9: 4900 | L9: {=780*2} -> 1560 | M9: {=_xlfn.IFERROR(K9+L9,50000)} -> 6460 | N9: 3 | O9: du vendredi 14h à dimanche fin d'après-midi | P9: Non | Q9: Non | R9: 220 | S9: 180 | T9: 2 gîtes | U9: 38 | V9: Non | W9: {=IF(J9<2.1,1,0)+IF(M9<'Budget - Budget'!$C$3,2,0)+IF(S9<'Invités'!$B$91,0,1)+IF(U9>'Invités'!$P$91,2,0)+IF(V9="Non",0,1)+IF(Q9="Oui",1,0)+IF(P9="Non",2,0)+IF(N9>2,2,0)+IF(M9>15000,-2,0)} -> 8 | X9: FALSE
B10: Château Amecourt | C10: TRUE | D10: TRUE | E10: TRUE | F10: FALSE | G10: https://www.mariages.net/chateau-mariage/chateau-amecourt--e136220 | H10: 2, Rue du Buisson de Bleu 27140 Amécourt (Eure) | I10: 1h20 | J10: 1.33 | K10: 4800 | L10: 2870 | M10: {=_xlfn.IFERROR(K10+L10,50000)} -> 7670 | N10: 3 | O10: du vendredi 18h au dimanche 17h | P10: Non | Q10: Non | R10: 130 | S10: 130 | T10: 16 | U10: 40 | V10: Oui | W10: {=IF(J10<2.1,1,0)+IF(M10<'Budget - Budget'!$C$3,2,0)+IF(S10<'Invités'!$B$91,0,1)+IF(U10>'Invités'!$P$91,2,0)+IF(V10="Non",0,1)+IF(Q10="Oui",1,0)+IF(P10="Non",2,0)+IF(N10>2,2,0)+IF(M10>15000,-2,0)} -> 9 | X10: FALSE
B11: Le Château de Motteux | C11: TRUE | D11: TRUE | E11: TRUE | F11: FALSE | G11: https://www.mariages.net/chateau-mariage/le-chateau-de-motteux--e195221 | H11: Château de Motteux 77130 Marolles-sur-Seine (Seine-et-Marne) | I11: 1h45 | J11: 1.75 | K11: 5500 | L11: 2450 | M11: {=_xlfn.IFERROR(K11+L11,50000)} -> 7950 | N11: 3 | O11: Vendredi 17h00 au dimanche 15h00 | P11: Non | Q11: Non | R11: 340 | S11: 200 | T11: 9 | U11: 45 | V11: Non | W11: {=IF(J11<2.1,1,0)+IF(M11<'Budget - Budget'!$C$3,2,0)+IF(S11<'Invités'!$B$91,0,1)+IF(U11>'Invités'!$P$91,2,0)+IF(V11="Non",0,1)+IF(Q11="Oui",1,0)+IF(P11="Non",2,0)+IF(N11>2,2,0)+IF(M11>15000,-2,0)} -> 8 | X11: FALSE
B12: Manoir des Foulons | C12: TRUE | D12: TRUE | E12: TRUE | F12: FALSE | G12: https://www.mariages.net/domaine-mariage/manoir-des-foulons--e8243 | H12: 1 Chemin des Foulons 78790 Rosay (Yvelines) | I12: 55min | J12: 0.92 | K12: 6400 | L12: 2785 | M12: {=_xlfn.IFERROR(K12+L12,50000)} -> 9185 | N12: 3 | O12: du vendredi 17h au dimanche 17h | P12: Non | Q12: Non | R12: 250 | S12: 200 | T12: 13 | U12: 33 | V12: Non | W12: {=IF(J12<2.1,1,0)+IF(M12<'Budget - Budget'!$C$3,2,0)+IF(S12<'Invités'!$B$91,0,1)+IF(U12>'Invités'!$P$91,2,0)+IF(V12="Non",0,1)+IF(Q12="Oui",1,0)+IF(P12="Non",2,0)+IF(N12>2,2,0)+IF(M12>15000,-2,0)} -> 8 | X12: FALSE
B13: Le Domaine de Grisien | C13: TRUE | D13: TRUE | E13: TRUE | F13: FALSE | G13: https://www.mariages.net/domaine-mariage/le-domaine-de-grisien--e381421 | H13: Ferme de Grisien Lieu dit Grisien 77540 Voinsles (Seine-et-Marne) | I13: 1h40 | J13: 1.67 | K13: 8000 | L13: 1500 | M13: {=_xlfn.IFERROR(K13+L13,50000)} -> 9500 | N13: 3 | O13: DU VENDREDI 10H JUSQU’AU DIMANCHE 17H | P13: Non | Q13: Non | R13: 200 | S13: 180 | T13: 14 | U13: 47 | V13: Non | W13: {=IF(J13<2.1,1,0)+IF(M13<'Budget - Budget'!$C$3,2,0)+IF(S13<'Invités'!$B$91,0,1)+IF(U13>'Invités'!$P$91,2,0)+IF(V13="Non",0,1)+IF(Q13="Oui",1,0)+IF(P13="Non",2,0)+IF(N13>2,2,0)+IF(M13>15000,-2,0)} -> 8 | X13: FALSE
B14: Les Jardins de Joséphine | C14: TRUE | D14: TRUE | E14: TRUE | F14: TRUE | G14: https://www.mariages.net/salle-mariage/les-jardins-de-josephine--e152850 | H14: 3, Rue des Quinconces 27000 Évreux (Eure) | I14: 1h20 | J14: 1.33 | K14: 9900 | L14: 0 | M14: {=_xlfn.IFERROR(K14+L14,50000)} -> 9900 | N14: 3 | O14: du vendredi 17h au dimanche 17h | P14: Non | Q14: Non | R14: 250 | S14: 160 | T14: 14 | U14: 31 | V14: Non | W14: {=IF(J14<2.1,1,0)+IF(M14<'Budget - Budget'!$C$3,2,0)+IF(S14<'Invités'!$B$91,0,1)+IF(U14>'Invités'!$P$91,2,0)+IF(V14="Non",0,1)+IF(Q14="Oui",1,0)+IF(P14="Non",2,0)+IF(N14>2,2,0)+IF(M14>15000,-2,0)} -> 8 | X14: TRUE
B15: Domaine de Coulonge | C15: TRUE | D15: TRUE | E15: TRUE | F15: FALSE | G15: https://www.mariages.net/domaine-mariage/domaine-de-coulonge--e195353 | H15: 2, Route de Damville 27240 Sylvains-les-Moulins (Eure) | I15: 1h30 | J15: 1.5 | K15: 6400 | L15: 3502 | M15: {=_xlfn.IFERROR(K15+L15,50000)} -> 9902 | N15: 3 | O15: du vendredi 9h au dimanche 17h | P15: Non | Q15: Non | R15: 380 | S15: 380 | T15: 16 | U15: 48 | V15: Non | W15: {=IF(J15<2.1,1,0)+IF(M15<'Budget - Budget'!$C$3,2,0)+IF(S15<'Invités'!$B$91,0,1)+IF(U15>'Invités'!$P$91,2,0)+IF(V15="Non",0,1)+IF(Q15="Oui",1,0)+IF(P15="Non",2,0)+IF(N15>2,2,0)+IF(M15>15000,-2,0)} -> 8 | X15: FALSE
B16: Le Nomade Lodge | C16: TRUE | D16: TRUE | E16: TRUE | F16: FALSE | G16: https://www.mariages.net/salle-mariage/le-nomade-lodge--e41965 | H16: RD 227 77720 La Chapelle-Gauthier (Seine-et-Marne) | I16: 1h30 | J16: 1.5 | K16: 9010 | L16: {=72*45} -> 3240 | M16: {=_xlfn.IFERROR(K16+L16,50000)} -> 12250 | N16: 3 | O16: DU VENDREDI 10H JUSQU’AU DIMANCHE 18H - pas privatisé mais grand domaine | P16: Non | Q16: Non | R16: 250 | S16: 250 | T16: 70 | U16: 230 | V16: Non | W16: {=IF(J16<2.1,1,0)+IF(M16<'Budget - Budget'!$C$3,2,0)+IF(S16<'Invités'!$B$91,0,1)+IF(U16>'Invités'!$P$91,2,0)+IF(V16="Non",0,1)+IF(Q16="Oui",1,0)+IF(P16="Non",2,0)+IF(N16>2,2,0)+IF(M16>15000,-2,0)} -> 10 | X16: FALSE
B17: La Ferme d'Armenon | C17: TRUE | D17: TRUE | E17: TRUE | F17: TRUE | G17: https://www.mariages.net/domaine-mariage/la-ferme-darmenon--e151906 | H17: Ferme d'Armenon 91470 Les Molières (Essonne) | I17: 55min | J17: 0.92 | K17: 10100 | L17: 4400 | M17: {=_xlfn.IFERROR(K17+L17,50000)} -> 14500 | N17: 3 | O17: (vendredi matin à dimanche 18h) | P17: Non | Q17: Non | R17: 200 | S17: 200 | T17: 19 | U17: 57 | V17: Non | W17: {=IF(J17<2.1,1,0)+IF(M17<'Budget - Budget'!$C$3,2,0)+IF(S17<'Invités'!$B$91,0,1)+IF(U17>'Invités'!$P$91,2,0)+IF(V17="Non",0,1)+IF(Q17="Oui",1,0)+IF(P17="Non",2,0)+IF(N17>2,2,0)+IF(M17>15000,-2,0)} -> 8 | X17: FALSE
B18: La Ferme du Grand Chemin | C18: TRUE | D18: TRUE | E18: FALSE | G18: https://www.mariages.net/domaine-mariage/la-ferme-du-grand-chemin--e102933 | H18: 20, Route de Vétheuil 95510 Vienne-en-Arthies (Val-d'Oise) | I18: 1h | J18: 1 | K18: {=5900+600} -> 6500 | L18: 2428 | M18: {=_xlfn.IFERROR(K18+L18,50000)} -> 8928 | N18: 2 | O18: Samedi au dimanche 16h + traiteur imposé + vendredi que pour installer la déco | P18: Non | Q18: Non | R18: 350 | S18: 350 | T18: 23 | U18: 63 | V18: Non | W18: {=IF(J18<2.1,1,0)+IF(M18<'Budget - Budget'!$C$3,2,0)+IF(S18<'Invités'!$B$91,0,1)+IF(U18>'Invités'!$P$91,2,0)+IF(V18="Non",0,1)+IF(Q18="Oui",1,0)+IF(P18="Non",2,0)+IF(N18>2,2,0)+IF(M18>15000,-2,0)} -> 6 | X18: FALSE
B19: Domaine des Prévanches | C19: TRUE | D19: TRUE | E19: TRUE | F19: FALSE | G19: https://www.mariages.net/domaine-mariage/domaine-des-prevanches--e119212 | H19: centre ville 27120 Boisset-les-Prévanches (Eure) | I19: 1h | J19: 1 | K19: 12700 | L19: 0 | M19: {=_xlfn.IFERROR(K19+L19,50000)} -> 12700 | N19: 3 | O19: du vendredi au dimanche | P19: Non | Q19: Non | R19: 300 | S19: 200 | T19: 25 | U19: 80 | V19: Non | W19: {=IF(J19<2.1,1,0)+IF(M19<'Budget - Budget'!$C$3,2,0)+IF(S19<'Invités'!$B$91,0,1)+IF(U19>'Invités'!$P$91,2,0)+IF(V19="Non",0,1)+IF(Q19="Oui",1,0)+IF(P19="Non",2,0)+IF(N19>2,2,0)+IF(M19>15000,-2,0)} -> 10 | X19: FALSE
B20: Domaine de Bontemps | C20: TRUE | D20: TRUE | E20: TRUE | G20: https://www.mariages.net/domaine-mariage/domaine-de-bontemps--e333446 | H20: Ferme des Aulnoys Bontemps 02310 Domptin (Aisne) | I20: 1h50 | J20: 1.83 | K20: 5500 | L20: 600 | M20: {=_xlfn.IFERROR(K20+L20,50000)} -> 6100 | N20: 3 | O20: Du vendredi 9h à 18h pour l’installation et du samedi 9h au dimanche 18h | P20: Non | Q20: Non | R20: 230 | S20: 230 | T20: 13 | U20: 45 | V20: Non | W20: {=IF(J20<2.1,1,0)+IF(M20<'Budget - Budget'!$C$3,2,0)+IF(S20<'Invités'!$B$91,0,1)+IF(U20>'Invités'!$P$91,2,0)+IF(V20="Non",0,1)+IF(Q20="Oui",1,0)+IF(P20="Non",2,0)+IF(N20>2,2,0)+IF(M20>15000,-2,0)} -> 8 | X20: FALSE
B21: Les Blés Verts | C21: TRUE | D21: TRUE | E21: TRUE | F21: TRUE | G21: https://www.mariages.net/salle-mariage/les-bles-verts--e149476 | H21: 6, Rue de la Grande Ferme 27190 Conches-en-Ouche (Eure) | I21: 1h50 | J21: 1.83 | K21: 3650 | L21: 0 | M21: {=_xlfn.IFERROR(K21+L21,50000)} -> 3650 | N21: 3 | O21: Vendredi 11h00 au dimanche 17h00 | P21: Non | Q21: Non | R21: 120 | S21: 120 | T21: 9 | U21: 35 | V21: Non | W21: {=IF(J21<2.1,1,0)+IF(M21<'Budget - Budget'!$C$3,2,0)+IF(S21<'Invités'!$B$91,0,1)+IF(U21>'Invités'!$P$91,2,0)+IF(V21="Non",0,1)+IF(Q21="Oui",1,0)+IF(P21="Non",2,0)+IF(N21>2,2,0)+IF(M21>15000,-2,0)} -> 8 | X21: FALSE
B22: Domaine de la Croix Sauvalle | C22: TRUE | D22: TRUE | E22: TRUE | F22: FALSE | G22: https://www.mariages.net/domaine-mariage/domaine-de-la-croix-sauvalle--e180437 | H22: 6, Rue de la Croix Sauvalle 27510 Forêt-la-Folie (Eure) | I22: 1h15 | J22: 1.25 | K22: 5300 | L22: {=810+780} -> 1590 | M22: {=_xlfn.IFERROR(K22+L22,50000)} -> 6890 | N22: 3 | O22: Le vendredi 11h00 (pour apporter vos décorations que nous installerons) Et du Samedi 9h00 au Dimanche 16h00 | P22: Non | Q22: Non | R22: 120 | S22: 120 | T22: 5 | U22: 26 | V22: Non | W22: {=IF(J22<2.1,1,0)+IF(M22<'Budget - Budget'!$C$3,2,0)+IF(S22<'Invités'!$B$91,0,1)+IF(U22>'Invités'!$P$91,2,0)+IF(V22="Non",0,1)+IF(Q22="Oui",1,0)+IF(P22="Non",2,0)+IF(N22>2,2,0)+IF(M22>15000,-2,0)} -> 8 | X22: FALSE
B23: Domaine de la Volière | C23: TRUE | D23: TRUE | E23: TRUE | F23: FALSE | G23: https://bridebook.com/fr/wedding-venues/domaine-de-la-voli-re-sainte-maure-de-touraine-indre-et-loire-frBXdAvKg6 | H23: La Volière, Sainte-Maure-de-Touraine, Indre-et-Loire, 37800, Centre-Val de Loire, France | I23: 3h15 | J23: 3.25 | K23: 4370 | L23: 2740 | M23: {=_xlfn.IFERROR(K23+L23,50000)} -> 7110 | N23: 4 | O23: du vendredi 10 h au lundi 10 h | P23: Non | Q23: Non | R23: 350 | S23: 200 | T23: 10 | U23: 30 | V23: Non | W23: {=IF(J23<2.1,1,0)+IF(M23<'Budget - Budget'!$C$3,2,0)+IF(S23<'Invités'!$B$91,0,1)+IF(U23>'Invités'!$P$91,2,0)+IF(V23="Non",0,1)+IF(Q23="Oui",1,0)+IF(P23="Non",2,0)+IF(N23>2,2,0)+IF(M23>15000,-2,0)} -> 7 | X23: FALSE
B24: Pont-Chevron | C24: TRUE | D24: TRUE | E24: TRUE | F24: FALSE | G24: https://bridebook.com/fr/wedding-venues/pont-chevron-ouzouer-sur-tr-z-e-loiret-frm8zlz2gR | H24: Château de Pont-Chevron , Ouzouer-sur-Trézée, Loiret, 45250, Centre-Val de Loire, France | I24: 2h30 | J24: 2.5 | K24: 5700 | L24: 2760 | M24: {=_xlfn.IFERROR(K24+L24,50000)} -> 8460 | N24: 3 | O24: du vendredi 10h au dimanche 14h | P24: Non | Q24: Non | R24: 1200 | S24: 300 | T24: 13 | U24: 44 | V24: Non | W24: {=IF(J24<2.1,1,0)+IF(M24<'Budget - Budget'!$C$3,2,0)+IF(S24<'Invités'!$B$91,0,1)+IF(U24>'Invités'!$P$91,2,0)+IF(V24="Non",0,1)+IF(Q24="Oui",1,0)+IF(P24="Non",2,0)+IF(N24>2,2,0)+IF(M24>15000,-2,0)} -> 7 | X24: FALSE
B25: Château de Laborde Saint-Martin | C25: TRUE | D25: TRUE | E25: TRUE | F25: FALSE | G25: https://bridebook.com/fr/wedding-venues/ch-teau-de-laborde-saint-martin-cand-sur-beuvron-loir-et-cher-frA8xEAaX0 | H25: 53 rue du Château, Candé-sur-Beuvron, Loir-et-Cher, 41120, Centre-Val de Loire, France | I25: 2h45 | J25: 2.75 | K25: 7500 | L25: 2000 | M25: {=_xlfn.IFERROR(K25+L25,50000)} -> 9500 | N25: 3 | O25: vendredi à partir de 15 heures au dimanche 17h | P25: Non | Q25: Non | R25: 280 | S25: 140 | T25: 21 | U25: 42 | V25: Non | W25: {=IF(J25<2.1,1,0)+IF(M25<'Budget - Budget'!$C$3,2,0)+IF(S25<'Invités'!$B$91,0,1)+IF(U25>'Invités'!$P$91,2,0)+IF(V25="Non",0,1)+IF(Q25="Oui",1,0)+IF(P25="Non",2,0)+IF(N25>2,2,0)+IF(M25>15000,-2,0)} -> 7 | X25: FALSE
B26: Manoir de Vacheresses | C26: TRUE | D26: TRUE | E26: TRUE | F26: TRUE | G26: https://www.mariages.net/domaine-mariage/manoir-de-vacheresses--e148581 | H26: Rue du Manoir 28210 Vacheresses-les-Basses (Eure-et-Loir) | I26: 1h15 | J26: 1.25 | K26: 7050 | L26: 2500 | M26: {=_xlfn.IFERROR(K26+L26,50000)} -> 9550 | N26: 3 | O26: du vendredi 14h (préparatifs) au dimanche 17h (brunch) : | P26: Non | Q26: Non | R26: 110 | S26: 110 | T26: 9 | U26: 21 | V26: Non | W26: {=IF(J26<2.1,1,0)+IF(M26<'Budget - Budget'!$C$3,2,0)+IF(S26<'Invités'!$B$91,0,1)+IF(U26>'Invités'!$P$91,2,0)+IF(V26="Non",0,1)+IF(Q26="Oui",1,0)+IF(P26="Non",2,0)+IF(N26>2,2,0)+IF(M26>15000,-2,0)} -> 8 | X26: FALSE
B27: Chateau Hazeville | C27: TRUE | D27: TRUE | E27: TRUE | F27: FALSE | G27: https://bridebook.com/fr/wedding-venues/chateau-hazeville-wy-dit-joli-village-val-d-oise-fr0X22aBQX | H27: Château d'Hazeville, Wy-dit-Joli-Village, Val-d'Oise, 95420, Île-de-France, France | I27: 1h | J27: 1 | K27: 9360 | L27: 810 | M27: {=_xlfn.IFERROR(K27+L27,50000)} -> 10170 | N27: 3 | O27: du vendredi 18h au dimanche 14h | P27: Non | Q27: Non | R27: 160 | S27: 160 | T27: 12 | U27: 45 | V27: Oui | W27: {=IF(J27<2.1,1,0)+IF(M27<'Budget - Budget'!$C$3,2,0)+IF(S27<'Invités'!$B$91,0,1)+IF(U27>'Invités'!$P$91,2,0)+IF(V27="Non",0,1)+IF(Q27="Oui",1,0)+IF(P27="Non",2,0)+IF(N27>2,2,0)+IF(M27>15000,-2,0)} -> 9 | X27: FALSE
B28: Château de Villette | C28: TRUE | D28: TRUE | E28: TRUE | F28: FALSE | G28: https://bridebook.com/fr/wedding-venues/ch-teau-de-villette-sennely-loiret-fr4XD1rLgo | H28: Route de Sennely, Menestreau en Villette, Loiret, 45240, Centre-Val de Loire, France | I28: 2h30 | J28: 2.5 | K28: 7877 | L28: 3106 | M28: {=_xlfn.IFERROR(K28+L28,50000)} -> 10983 | N28: 3 | O28: vendredi 13h au dimanche 19h | P28: Non | Q28: Non | R28: 300 | S28: 300 | T28: 24 | U28: 60 | V28: Non | W28: {=IF(J28<2.1,1,0)+IF(M28<'Budget - Budget'!$C$3,2,0)+IF(S28<'Invités'!$B$91,0,1)+IF(U28>'Invités'!$P$91,2,0)+IF(V28="Non",0,1)+IF(Q28="Oui",1,0)+IF(P28="Non",2,0)+IF(N28>2,2,0)+IF(M28>15000,-2,0)} -> 7 | X28: FALSE
B29: Le Moulin de Pommeuse | C29: TRUE | D29: TRUE | E29: TRUE | F29: FALSE | G29: https://www.mariages.net/domaine-mariage/le-moulin-de-pommeuse--e155990 | H29: 32, avenue du Général Huerne 77515 Pommeuse (Seine-et-Marne) | I29: 1h35 | J29: 1.58 | K29: 5500 | L29: 5530 | M29: {=_xlfn.IFERROR(K29+L29,50000)} -> 11030 | N29: 3 | O29: vendredi 15h au dimanche 18h | P29: Non | Q29: Non | R29: 120 | S29: 100 | T29: 25 | U29: 75 | V29: Non | W29: {=IF(J29<2.1,1,0)+IF(M29<'Budget - Budget'!$C$3,2,0)+IF(S29<'Invités'!$B$91,0,1)+IF(U29>'Invités'!$P$91,2,0)+IF(V29="Non",0,1)+IF(Q29="Oui",1,0)+IF(P29="Non",2,0)+IF(N29>2,2,0)+IF(M29>15000,-2,0)} -> 10 | X29: FALSE
B30: Domaine des Coccinelles | C30: TRUE | D30: TRUE | E30: TRUE | F30: FALSE | G30: https://www.mariages.net/domaine-mariage/domaine-des-coccinelles--e235316 | H30: La Tuilerie 91470 Angervilliers (Essonne) | I30: 1h10 | J30: 1.17 | K30: 13500 | L30: 9120 | M30: {=_xlfn.IFERROR(K30+L30,50000)} -> 22620 | N30: 3 | O30: Vendredi 11h00 au dimanche 17h00 | P30: Non | Q30: Non | R30: 200 | S30: 200 | T30: 16 | U30: 55 | V30: Oui | W30: {=IF(J30<2.1,1,0)+IF(M30<'Budget - Budget'!$C$3,2,0)+IF(S30<'Invités'!$B$91,0,1)+IF(U30>'Invités'!$P$91,2,0)+IF(V30="Non",0,1)+IF(Q30="Oui",1,0)+IF(P30="Non",2,0)+IF(N30>2,2,0)+IF(M30>15000,-2,0)} -> 5 | X30: FALSE
B31: Les Tourelles de Fonville | C31: TRUE | D31: TRUE | E31: TRUE | F31: TRUE | G31: https://www.mariages.net/domaine-mariage/les-tourelles-de-fonville--e185949 | H31: 5, Rue de la Chapelle 28210 Le Boullay-Mivoye (Eure-et-Loir) | I31: 1h15 | J31: 1.25 | K31: 9500 | L31: 0 | M31: {=_xlfn.IFERROR(K31+L31,50000)} -> 9500 | N31: 3 | O31: du vendredi 12h au dimanche 17h | P31: Non | Q31: Non | R31: 130 | S31: 130 | T31: 13 | U31: 36 | V31: Non | W31: {=IF(J31<2.1,1,0)+IF(M31<'Budget - Budget'!$C$3,2,0)+IF(S31<'Invités'!$B$91,0,1)+IF(U31>'Invités'!$P$91,2,0)+IF(V31="Non",0,1)+IF(Q31="Oui",1,0)+IF(P31="Non",2,0)+IF(N31>2,2,0)+IF(M31>15000,-2,0)} -> 8 | X31: FALSE
B32: Domaine de la Thibaudière | C32: TRUE | D32: TRUE | E32: FALSE | G32: https://bridebook.com/fr/shortlist/venues/domaine-de-la-thibaudi-re-faverolles-eure-et-loir-frog49pWYv | H32: Route Du Bout Au Duhay, Faverolles, Eure-et-Loir, 28210, Centre-Val de Loire, France | I32: 1h15 | J32: 1.25 | K32: 22000 | L32: 0 | M32: {=_xlfn.IFERROR(K32+L32,50000)} -> 22000 | N32: 3 | O32: du vendredi 17h00 au dimanche 15h00 | P32: Non | Q32: Non | R32: 180 | S32: 160 | T32: 16 | U32: 56 | V32: Oui | W32: {=IF(J32<2.1,1,0)+IF(M32<'Budget - Budget'!$C$3,2,0)+IF(S32<'Invités'!$B$91,0,1)+IF(U32>'Invités'!$P$91,2,0)+IF(V32="Non",0,1)+IF(Q32="Oui",1,0)+IF(P32="Non",2,0)+IF(N32>2,2,0)+IF(M32>15000,-2,0)} -> 5 | X32: FALSE
B33: Le Clos de l'Orangerie | C33: TRUE | D33: TRUE | E33: FALSE | G33: https://www.mariages.net/domaine-mariage/le-clos-de-lorangerie--e145905 | H33: D110 78710 Rosny-sur-Seine (Yvelines) | I33: 50min | J33: 0.83 | K33: {=65000} -> 65000 | L33: 0 | M33: {=_xlfn.IFERROR(K33+L33,50000)} -> 65000 | N33: 3 | O33: Vendredi 11h00 au dimanche 17h00 (l’hébergement pour 130 personnes, ainsi que la partie technique et le DJ.) | P33: Non | Q33: Non | R33: 400 | S33: 400 | T33: 30 | U33: 60 | V33: Oui | W33: {=IF(J33<2.1,1,0)+IF(M33<'Budget - Budget'!$C$3,2,0)+IF(S33<'Invités'!$B$91,0,1)+IF(U33>'Invités'!$P$91,2,0)+IF(V33="Non",0,1)+IF(Q33="Oui",1,0)+IF(P33="Non",2,0)+IF(N33>2,2,0)+IF(M33>15000,-2,0)} -> 5 | X33: FALSE
B34: L'Orangerie de l’Orée du Bois | C34: TRUE | D34: TRUE | E34: FALSE | G34: https://www.mariages.net/domaine-mariage/lorangerie-de-l-oree-du-bois--e351105 | H34: Chemin de la Côte Blanche 78710 Rosny-sur-Seine (Yvelines) | I34: 55min | J34: 0.92 | K34: {=65000} -> 65000 | L34: 0 | M34: {=_xlfn.IFERROR(K34+L34,50000)} -> 65000 | N34: 3 | O34: Vendredi 11h00 au dimanche 17h00 - plus de disponibilités en 2027 | P34: Non | Q34: Non | R34: 500 | S34: 500 | T34: 23 | U34: 55 | V34: Oui | W34: {=IF(J34<2.1,1,0)+IF(M34<'Budget - Budget'!$C$3,2,0)+IF(S34<'Invités'!$B$91,0,1)+IF(U34>'Invités'!$P$91,2,0)+IF(V34="Non",0,1)+IF(Q34="Oui",1,0)+IF(P34="Non",2,0)+IF(N34>2,2,0)+IF(M34>15000,-2,0)} -> 5 | X34: FALSE
B35: Domaine de Saint Vigor | C35: TRUE | D35: TRUE | E35: TRUE | F35: TRUE | G35: https://www.mariages.net/domaine-mariage/domaine-de-saint-vigor--e194877 | H35: 2, Route des Buissonnets 27930 Saint-Vigor (Eure) | I35: 1h | J35: 2 | K35: 4550 | L35: 4590 | M35: {=_xlfn.IFERROR(K35+L35,50000)} -> 9140 | N35: 3 | O35: Du vendredi 17h au dimanche 17h - traiteur imposé, sinon 600€ droit d’accès | P35: Oui | Q35: Non | R35: 130 | S35: 130 | T35: 14 | U35: 60 | V35: Non | W35: {=IF(J35<2.1,1,0)+IF(M35<'Budget - Budget'!$C$3,2,0)+IF(S35<'Invités'!$B$91,0,1)+IF(U35>'Invités'!$P$91,2,0)+IF(V35="Non",0,1)+IF(Q35="Oui",1,0)+IF(P35="Non",2,0)+IF(N35>2,2,0)+IF(M35>15000,-2,0)} -> 6 | X35: FALSE
B36: Château d'Hermival | C36: TRUE | D36: TRUE | E36: TRUE | F36: FALSE | G36: https://www.mariages.net/chateau-mariage/chateau-dhermival--e194737 | H36: 2686, Route de Cormeilles 14100 Hermival-les-Vaux (Calvados) | I36: 2h10 | J36: 2.17 | K36: 7500 | L36: 750 | M36: {=_xlfn.IFERROR(K36+L36,50000)} -> 8250 | N36: 3 | O36: du vendredi 14h au dimanche 17h | P36: Non | Q36: Non | R36: 120 | S36: 120 | T36: 10 | U36: 38 | V36: Non | W36: {=IF(J36<2.1,1,0)+IF(M36<'Budget - Budget'!$C$3,2,0)+IF(S36<'Invités'!$B$91,0,1)+IF(U36>'Invités'!$P$91,2,0)+IF(V36="Non",0,1)+IF(Q36="Oui",1,0)+IF(P36="Non",2,0)+IF(N36>2,2,0)+IF(M36>15000,-2,0)} -> 7 | X36: FALSE
B37: Domaine de Champignolles | C37: TRUE | D37: TRUE | E37: TRUE | F37: FALSE | G37: https://www.mariages.net/domaine-mariage/domaine-de-champignolles--e329152 | H37: Domaine de champignolles 60590 Sérifontaine (Oise) | I37: 1h20 | J37: 1.33 | K37: 6000 | L37: 4000 | M37: {=_xlfn.IFERROR(K37+L37,50000)} -> 10000 | N37: 4 | O37: du vendredi dès 9h au lundi 10h | P37: Non | Q37: Non | R37: 500 | S37: 500 | T37: 8 | U37: 30 | V37: Non | W37: {=IF(J37<2.1,1,0)+IF(M37<'Budget - Budget'!$C$3,2,0)+IF(S37<'Invités'!$B$91,0,1)+IF(U37>'Invités'!$P$91,2,0)+IF(V37="Non",0,1)+IF(Q37="Oui",1,0)+IF(P37="Non",2,0)+IF(N37>2,2,0)+IF(M37>15000,-2,0)} -> 8 | X37: FALSE
B38: Château de Maudétour | C38: TRUE | D38: TRUE | E38: TRUE | F38: TRUE | G38: https://www.mariages.net/chateau-mariage/chateau-de-maudetour--e137675 | H38: 1, Allée des Tilleuls 95420 Maudétour-en-Vexin (Val-d'Oise) | I38: 55min | J38: 0.92 | K38: 6950 | L38: 5300 | M38: {=_xlfn.IFERROR(K38+L38,50000)} -> 12250 | N38: 3 | O38: du vendredi 17h au dimanche 17h | P38: Non | Q38: Non | R38: 250 | S38: 250 | T38: 19 | U38: 46 | V38: Non | W38: {=IF(J38<2.1,1,0)+IF(M38<'Budget - Budget'!$C$3,2,0)+IF(S38<'Invités'!$B$91,0,1)+IF(U38>'Invités'!$P$91,2,0)+IF(V38="Non",0,1)+IF(Q38="Oui",1,0)+IF(P38="Non",2,0)+IF(N38>2,2,0)+IF(M38>15000,-2,0)} -> 8 | X38: FALSE
B39: Château de Laverdines | C39: TRUE | D39: TRUE | E39: TRUE | F39: FALSE | G39: https://bridebook.com/fr/wedding-venues/ch-teau-de-laverdines-baugy-cher-frqYNwG68V | H39: 2A Route de la Chapelle, Baugy, Cher, 18800, Centre-Val de Loire, France | I39: 3h30 | J39: 3.5 | K39: {=9900+4500} -> 14400 | L39: 0 | M39: {=_xlfn.IFERROR(K39+L39,50000)} -> 14400 | N39: 4 | O39: Vendredi 11h au lundi 17h - attention il faut louer une tente 4,5K€ | P39: Non | Q39: Oui | R39: 250 | S39: 150 | T39: 23 | U39: 42 | V39: Non | W39: {=IF(J39<2.1,1,0)+IF(M39<'Budget - Budget'!$C$3,2,0)+IF(S39<'Invités'!$B$91,0,1)+IF(U39>'Invités'!$P$91,2,0)+IF(V39="Non",0,1)+IF(Q39="Oui",1,0)+IF(P39="Non",2,0)+IF(N39>2,2,0)+IF(M39>15000,-2,0)} -> 8 | X39: FALSE
B40: Château Le Chereau et Domaine Les Poultières | C40: TRUE | D40: TRUE | E40: FALSE | G40: https://bridebook.com/fr/wedding-venues/ch-teau-le-chereau-et-domaine-les-poulti-res-montrieux-en-sologne-loir-et-cher-frEqYZxBX2 | H40: Montrieux-en-Sologne, Loir-et-Cher, Centre-Val de Loire, France | I40: 2h40 | J40: 2.67 | K40: {=12750+5000} -> 17750 | L40: 0 | M40: {=_xlfn.IFERROR(K40+L40,50000)} -> 17750 | N40: 3 | O40: Vendredi (arrivée a midi et plus tôt si possible) jusqu’au Dimanche 16H00 - Que 80 assis en intérieur, pour plus, il faut louer une tente à 5K€ | P40: Non | Q40: Non | R40: 300 | S40: 200 | T40: 25 | U40: 62 | V40: Oui | W40: {=IF(J40<2.1,1,0)+IF(M40<'Budget - Budget'!$C$3,2,0)+IF(S40<'Invités'!$B$91,0,1)+IF(U40>'Invités'!$P$91,2,0)+IF(V40="Non",0,1)+IF(Q40="Oui",1,0)+IF(P40="Non",2,0)+IF(N40>2,2,0)+IF(M40>15000,-2,0)} -> 4 | X40: FALSE
B41: Le Prieuré de Vernelle | C41: TRUE | D41: TRUE | E41: FALSE | G41: https://www.mariages.net/domaine-mariage/le-prieure-de-vernelle--e8151 | H41: Route d'Evry, Lieu dit : Le Prieuré de Vernelle 77166 Grisy-Suisnes (Seine-et-Marne) | I41: 1h30 | J41: 1.5 | K41: 22500 | L41: 0 | M41: {=_xlfn.IFERROR(K41+L41,50000)} -> 22500 | N41: 3 | O41: du vendredi au dimanche | P41: Non | Q41: Non | R41: 200 | S41: 200 | T41: 18 | U41: 65 | V41: Non | W41: {=IF(J41<2.1,1,0)+IF(M41<'Budget - Budget'!$C$3,2,0)+IF(S41<'Invités'!$B$91,0,1)+IF(U41>'Invités'!$P$91,2,0)+IF(V41="Non",0,1)+IF(Q41="Oui",1,0)+IF(P41="Non",2,0)+IF(N41>2,2,0)+IF(M41>15000,-2,0)} -> 4 | X41: FALSE
B42: Abbaye du Trésor | C42: TRUE | D42: TRUE | E42: TRUE | G42: https://www.mariages.net/domaine-mariage/abbaye-du-tresor--e311894 | H42: 40, Route de l'Abbaye 27630 Bus-Saint-Rémy (Eure) | I42: 1h15 | J42: 1.25 | K42: 11500 | L42: 0 | M42: {=_xlfn.IFERROR(K42+L42,50000)} -> 11500 | N42: 3 | O42: du vendredi 12h au dimanche 17h | P42: Non | Q42: Non | R42: 250 | S42: 250 | T42: 7 | U42: 18 | V42: Non | W42: {=IF(J42<2.1,1,0)+IF(M42<'Budget - Budget'!$C$3,2,0)+IF(S42<'Invités'!$B$91,0,1)+IF(U42>'Invités'!$P$91,2,0)+IF(V42="Non",0,1)+IF(Q42="Oui",1,0)+IF(P42="Non",2,0)+IF(N42>2,2,0)+IF(M42>15000,-2,0)} -> 8 | X42: FALSE
B43: Le Val Gaudry | C43: TRUE | D43: TRUE | E43: TRUE | G43: https://www.mariages.net/domaine-mariage/le-val-gaudry--e277984 | H43: Le Tertre 61360 Montgaudry (Orne) | I43: 2h30 | J43: 2.5 | K43: 13800 | L43: 0 | M43: {=_xlfn.IFERROR(K43+L43,50000)} -> 13800 | N43: 4 | O43: du vendredi 12h au lundi 16h | P43: Non | Q43: Non | R43: 200 | S43: 200 | T43: 9 | U43: 28 | V43: Oui | W43: {=IF(J43<2.1,1,0)+IF(M43<'Budget - Budget'!$C$3,2,0)+IF(S43<'Invités'!$B$91,0,1)+IF(U43>'Invités'!$P$91,2,0)+IF(V43="Non",0,1)+IF(Q43="Oui",1,0)+IF(P43="Non",2,0)+IF(N43>2,2,0)+IF(M43>15000,-2,0)} -> 8 | X43: FALSE
B44: Le Village de Sully | C44: TRUE | D44: TRUE | E44: FALSE | G44: https://www.mariages.net/domaine-mariage/le-village-de-sully--e159056 | H44: D110 78710 Jouy-Mauvoisin (Yvelines) | I44: 50min | J44: 0.83 | K44: {=65000} -> 65000 | L44: 0 | M44: {=_xlfn.IFERROR(K44+L44,50000)} -> 65000 | N44: 3 | O44: Vendredi 11h00 au dimanche 17h00 (l’hébergement pour 130 personnes, ainsi que la partie technique et le DJ.) | P44: Non | Q44: Non | R44: 250 | S44: 250 | T44: 37 | U44: 74 | V44: Non | W44: {=IF(J44<2.1,1,0)+IF(M44<'Budget - Budget'!$C$3,2,0)+IF(S44<'Invités'!$B$91,0,1)+IF(U44>'Invités'!$P$91,2,0)+IF(V44="Non",0,1)+IF(Q44="Oui",1,0)+IF(P44="Non",2,0)+IF(N44>2,2,0)+IF(M44>15000,-2,0)} -> 4 | X44: FALSE
B45: Le Château de l'Orée du Bois | C45: TRUE | D45: TRUE | E45: FALSE | G45: https://www.mariages.net/chateau-mariage/le-chateau-de-loree-du-bois--e188956 | H45: Chemin de la Côte Blanche 78710 Rosny-sur-Seine (Yvelines) | I45: 55min | J45: 0.92 | K45: {=65000} -> 65000 | L45: 0 | M45: {=_xlfn.IFERROR(K45+L45,50000)} -> 65000 | N45: 3 | O45: Vendredi 11h00 au dimanche 17h00 - plus de disponibilités en 2027 | P45: Non | Q45: Non | R45: 120 | S45: 120 | T45: 23 | U45: 55 | V45: Oui | W45: {=IF(J45<2.1,1,0)+IF(M45<'Budget - Budget'!$C$3,2,0)+IF(S45<'Invités'!$B$91,0,1)+IF(U45>'Invités'!$P$91,2,0)+IF(V45="Non",0,1)+IF(Q45="Oui",1,0)+IF(P45="Non",2,0)+IF(N45>2,2,0)+IF(M45>15000,-2,0)} -> 5 | X45: FALSE
B46: La Catrache | C46: TRUE | D46: TRUE | E46: FALSE | G46: https://www.mariages.net/domaine-mariage/la-catrache--e10724 | H46: 17 bis, Rue de la Forêt - Guippereux 78125 Hermeray (Yvelines) | I46: 1h15 | J46: 1.25 | K46: {=6615+1700} -> 8315 | L46: 1370 | M46: {=_xlfn.IFERROR(K46+L46,50000)} -> 9685 | N46: 2 | O46: samedi 28 Août disponible de 17h00 à 03h00 au dimanche 29 Août, de 11h00 à 16h00 + traiteur imposé | P46: Oui | Q46: Non | R46: 150 | S46: 150 | T46: 9 | U46: 22 | V46: Oui | W46: {=IF(J46<2.1,1,0)+IF(M46<'Budget - Budget'!$C$3,2,0)+IF(S46<'Invités'!$B$91,0,1)+IF(U46>'Invités'!$P$91,2,0)+IF(V46="Non",0,1)+IF(Q46="Oui",1,0)+IF(P46="Non",2,0)+IF(N46>2,2,0)+IF(M46>15000,-2,0)} -> 5 | X46: FALSE
B47: Domaine de Vaujoly | C47: TRUE | D47: TRUE | E47: FALSE | G47: https://bridebook.com/fr/wedding-venues/le-domaine-de-vaujoly-courville-sur-eure-eure-et-loir-frEgQ3JQ8J | H47: Lieu Dit Le Vaujoly, 28190 Courville-sur-Eure | I47: 1h50 | J47: 1.83 | K47: 22000 | L47: 0 | M47: {=_xlfn.IFERROR(K47+L47,50000)} -> 22000 | N47: 3 | O47: Vendredi 17h00 au dimanche 15h00 | R47: 700 | S47: 350 | T47: 25 | U47: 76 | V47: Oui | W47: {=IF(J47<2.1,1,0)+IF(M47<'Budget - Budget'!$C$3,2,0)+IF(S47<'Invités'!$B$91,0,1)+IF(U47>'Invités'!$P$91,2,0)+IF(V47="Non",0,1)+IF(Q47="Oui",1,0)+IF(P47="Non",2,0)+IF(N47>2,2,0)+IF(M47>15000,-2,0)} -> 5 | X47: FALSE
B48: Domaine des Colombes | C48: TRUE | D48: TRUE | E48: TRUE | F48: TRUE | G48: https://www.mariages.net/domaine-mariage/domaine-des-colombes--e318080 | H48: La Chaise 28000 Bonneval (Eure-et-Loir) | I48: 2h | J48: 3 | K48: 10000 | L48: 4320 | M48: {=_xlfn.IFERROR(K48+L48,50000)} -> 14320 | N48: 3 | O48: Vendredi 11h00 au dimanche 17h00 | P48: Non | Q48: Non | R48: 800 | S48: 800 | T48: 8 | U48: 20 | V48: Non | W48: {=IF(J48<2.1,1,0)+IF(M48<'Budget - Budget'!$C$3,2,0)+IF(S48<'Invités'!$B$91,0,1)+IF(U48>'Invités'!$P$91,2,0)+IF(V48="Non",0,1)+IF(Q48="Oui",1,0)+IF(P48="Non",2,0)+IF(N48>2,2,0)+IF(M48>15000,-2,0)} -> 7 | X48: FALSE
B49: Moulin de Mistou | C49: TRUE | D49: TRUE | E49: FALSE | G49: https://www.mariages.net/domaine-mariage/moulin-de-mistou--e199379 | H49: 6, Route Départementale 402 77120 Mauperthuis (Seine-et-Marne) | I49: 1h40 | J49: 1.67 | K49: 6500 | L49: 1980 | M49: {=_xlfn.IFERROR(K49+L49,50000)} -> 8480 | N49: 3 | O49: vendredi 14h à dimanche 17h - traiteur du lieu obligatoire | P49: Oui | Q49: Non | R49: 130 | S49: 130 | T49: 8 | U49: 25 | V49: Non | W49: {=IF(J49<2.1,1,0)+IF(M49<'Budget - Budget'!$C$3,2,0)+IF(S49<'Invités'!$B$91,0,1)+IF(U49>'Invités'!$P$91,2,0)+IF(V49="Non",0,1)+IF(Q49="Oui",1,0)+IF(P49="Non",2,0)+IF(N49>2,2,0)+IF(M49>15000,-2,0)} -> 6 | X49: FALSE
B50: Hôtel Dolce by Wyndham Versailles – Domaine du Montcel | C50: TRUE | D50: TRUE | E50: FALSE | G50: https://www.mariages.net/domaine-mariage/hotel-dolce-by-wyndham-versailles-domaine-du-montcel--e302872 | H50: 2, Rue du Montcel 78350 Jouy-en-Josas (Yvelines) | I50: 35min | J50: 0.58 | K50: 18850 | L50: 0 | M50: {=_xlfn.IFERROR(K50+L50,50000)} -> 18850 | N50: 1 | O50: 1 | P50: Non | Q50: Non | R50: 250 | S50: 250 | T50: 178 | U50: 300 | V50: Oui | W50: {=IF(J50<2.1,1,0)+IF(M50<'Budget - Budget'!$C$3,2,0)+IF(S50<'Invités'!$B$91,0,1)+IF(U50>'Invités'!$P$91,2,0)+IF(V50="Non",0,1)+IF(Q50="Oui",1,0)+IF(P50="Non",2,0)+IF(N50>2,2,0)+IF(M50>15000,-2,0)} -> 5 | X50: FALSE
B51: Château Barthélemy | C51: TRUE | D51: TRUE | E51: FALSE | G51: https://www.mariages.net/chateau-mariage/chateau-barthelemy--e138571 | H51: 3, Route Nationale 191 78660 Paray-Douaville (Yvelines) | I51: 1h15 | J51: 1.25 | K51: 19900 | L51: 0 | M51: {=_xlfn.IFERROR(K51+L52,50000)} -> 19900 | N51: 1 | O51: 1 | P51: Non | Q51: Non | R51: 250 | S51: 250 | T51: 35 | U51: 88 | V51: Oui | W51: {=IF(J51<2.1,1,0)+IF(M51<'Budget - Budget'!$C$3,2,0)+IF(S51<'Invités'!$B$91,0,1)+IF(U51>'Invités'!$P$91,2,0)+IF(V51="Non",0,1)+IF(Q51="Oui",1,0)+IF(P51="Non",2,0)+IF(N51>2,2,0)+IF(M51>15000,-2,0)} -> 5 | X51: FALSE
B52: Château des Hauts de Provins | C52: TRUE | D52: TRUE | E52: FALSE | G52: https://www.mariages.net/chateau-mariage/chateau-des-hauts-de-provins--e245889 | H52: Route de Ferreux 77560 Champcenest (Seine-et-Marne) | I52: 2h | J52: 2 | K52: 20000 | L52: 0 | M52: {=_xlfn.IFERROR(K52+L52,50000)} -> 20000 | N52: 2 | O52: samedi 16h au dimanche 16h | P52: Non | Q52: Non | R52: 300 | S52: 300 | T52: 16 | U52: 52 | V52: Oui | W52: {=IF(J52<2.1,1,0)+IF(M52<'Budget - Budget'!$C$3,2,0)+IF(S52<'Invités'!$B$91,0,1)+IF(U52>'Invités'!$P$91,2,0)+IF(V52="Non",0,1)+IF(Q52="Oui",1,0)+IF(P52="Non",2,0)+IF(N52>2,2,0)+IF(M52>15000,-2,0)} -> 3 | X52: FALSE
B53: Le Petit Chateau de Barbizon | C53: TRUE | D53: TRUE | E53: FALSE | G53: https://www.mariages.net/chateau-mariage/le-petit-chateau-de-barbizon--e326194 | H53: Barbizon 77630 Barbizon (Seine-et-Marne) | I53: 1h20 | J53: 1.33 | K53: 10000 | L53: 9000 | M53: {=_xlfn.IFERROR(K53+L53,50000)} -> 19000 | N53: 3 | O53: du vendredi 16h au dimanche 17h - logements très chers | P53: Non | Q53: Non | R53: 300 | S53: 300 | T53: 15 | U53: 49 | V53: Oui | W53: {=IF(J53<2.1,1,0)+IF(M53<'Budget - Budget'!$C$3,2,0)+IF(S53<'Invités'!$B$91,0,1)+IF(U53>'Invités'!$P$91,2,0)+IF(V53="Non",0,1)+IF(Q53="Oui",1,0)+IF(P53="Non",2,0)+IF(N53>2,2,0)+IF(M53>15000,-2,0)} -> 5 | X53: FALSE
B54: Château de Bonaventure | C54: TRUE | D54: TRUE | E54: FALSE | G54: https://www.mariages.net/chateau-mariage/chateau-de-bonaventure--e200469 | H54: Château de Bonaventure 77120 Aulnoy (Seine-et-Marne) | I54: 1h40 | J54: 1.67 | K54: 20500 | L54: 6500 | M54: {=_xlfn.IFERROR(K54+L54,50000)} -> 27000 | N54: 3 | O54: Vendredi 15h00 au dimanche 16h00 | P54: Non | Q54: Non | R54: 150 | S54: 150 | T54: 14 | U54: 36 | V54: Oui | W54: {=IF(J54<2.1,1,0)+IF(M54<'Budget - Budget'!$C$3,2,0)+IF(S54<'Invités'!$B$91,0,1)+IF(U54>'Invités'!$P$91,2,0)+IF(V54="Non",0,1)+IF(Q54="Oui",1,0)+IF(P54="Non",2,0)+IF(N54>2,2,0)+IF(M54>15000,-2,0)} -> 5 | X54: FALSE
B55: Le Château de Beauvois | C55: TRUE | D55: TRUE | E55: FALSE | G55: https://bridebook.com/fr/wedding-venues/le-ch-teau-de-beauvois-saint-etienne-de-chigny-indre-et-loire-frqYNej6gV | H55: Route de Beauvois, Saint-Etienne-de-Chigny, Indre-et-Loire, 37230, Centre-Val de Loire, France | I55: 3h20 | J55: 3.33 | K55: 28000 | L55: 0 | M55: {=_xlfn.IFERROR(K55+L55,50000)} -> 28000 | N55: 3 | O55: du jour de votre arrivée à 16h00 jusqu'à 11h00 le lendemain | P55: Non | Q55: Non | R55: 100 | S55: 100 | T55: 35 | U55: 85 | V55: Oui | W55: {=IF(J55<2.1,1,0)+IF(M55<'Budget - Budget'!$C$3,2,0)+IF(S55<'Invités'!$B$91,0,1)+IF(U55>'Invités'!$P$91,2,0)+IF(V55="Non",0,1)+IF(Q55="Oui",1,0)+IF(P55="Non",2,0)+IF(N55>2,2,0)+IF(M55>15000,-2,0)} -> 6 | X55: FALSE
B56: La Dîme de Giverny | C56: TRUE | D56: TRUE | E56: TRUE | F56: TRUE | G56: https://www.mariages.net/domaine-mariage/la-dime-de-giverny--e131554 | H56: 2, Rue de la Dime 27620 Giverny (Eure) | I56: 1h | J56: 1 | K56: 12000 | L56: 0 | M56: {=_xlfn.IFERROR(K56+L56,50000)} -> 12000 | N56: 3 | O56: du vendredi au dimanche 15h | P56: Non | Q56: Non | R56: 120 | S56: 120 | T56: 6 | U56: 18 | V56: Non | W56: {=IF(J56<2.1,1,0)+IF(M56<'Budget - Budget'!$C$3,2,0)+IF(S56<'Invités'!$B$91,0,1)+IF(U56>'Invités'!$P$91,2,0)+IF(V56="Non",0,1)+IF(Q56="Oui",1,0)+IF(P56="Non",2,0)+IF(N56>2,2,0)+IF(M56>15000,-2,0)} -> 8 | X56: FALSE
B57: Le Moulin De Bully | C57: TRUE | D57: TRUE | E57: TRUE | G57: https://www.mariages.net/domaine-mariage/le-moulin-de-bully--e90741 | H57: 29, Route du Pont du Coudray 14320 Caen (Calvados) | I57: 2h30 | J57: 2.5 | K57: 9705 | L57: 0 | M57: {=_xlfn.IFERROR(K57+L57,50000)} -> 9705 | N57: 3 | O57: du vendredi 11h au dimanche 18h | P57: Oui | Q57: Non | R57: 160 | S57: 160 | T57: 7 | U57: 39 | V57: Non | W57: {=IF(J57<2.1,1,0)+IF(M57<'Budget - Budget'!$C$3,2,0)+IF(S57<'Invités'!$B$91,0,1)+IF(U57>'Invités'!$P$91,2,0)+IF(V57="Non",0,1)+IF(Q57="Oui",1,0)+IF(P57="Non",2,0)+IF(N57>2,2,0)+IF(M57>15000,-2,0)} -> 5 | X57: FALSE
B58: Ferme d'Orsonville | C58: TRUE | D58: TRUE | E58: FALSE | G58: https://www.mariages.net/domaine-mariage/ferme-dorsonville--e73782 | H58: Ferme d'Orsonville 77190 Villiers-en-Bière (Seine-et-Marne) | I58: 1h25 | J58: 1.42 | K58: 5240 | L58: 530 | M58: {=_xlfn.IFERROR(K58+L58,50000)} -> 5770 | N58: 3 | O58: du vendredi 14h au dimanche 20h - liste de traiteurs imposés | P58: Oui | Q58: Non | R58: 150 | S58: 120 | T58: 8 | U58: 25 | V58: Non | W58: {=IF(J58<2.1,1,0)+IF(M58<'Budget - Budget'!$C$3,2,0)+IF(S58<'Invités'!$B$91,0,1)+IF(U58>'Invités'!$P$91,2,0)+IF(V58="Non",0,1)+IF(Q58="Oui",1,0)+IF(P58="Non",2,0)+IF(N58>2,2,0)+IF(M58>15000,-2,0)} -> 6 | X58: FALSE
B59: Château de Chéronne | C59: TRUE | D59: TRUE | E59: FALSE | G59: https://www.mariages.net/domaine-mariage/chateau-de-cheronne--e7324 | H59: Château de Chéronne 72160 Tuffé (Sarthe) | I59: 2h15 | J59: 2.25 | K59: 9863 | L59: 0 | M59: {=_xlfn.IFERROR(K59+L59,50000)} -> 9863 | N59: 3 | O59: du vendredi 15h au dimanche 17h - traiteur imposé parmis une liste de 4 (inclus dans le prix : photobooth et feux d’artifices) | P59: Oui | Q59: Non | R59: 500 | S59: 280 | T59: 23 | U59: 50 | V59: Non | W59: {=IF(J59<2.1,1,0)+IF(M59<'Budget - Budget'!$C$3,2,0)+IF(S59<'Invités'!$B$91,0,1)+IF(U59>'Invités'!$P$91,2,0)+IF(V59="Non",0,1)+IF(Q59="Oui",1,0)+IF(P59="Non",2,0)+IF(N59>2,2,0)+IF(M59>15000,-2,0)} -> 5 | X59: FALSE
B60: Domaine Imodis | C60: TRUE | D60: TRUE | E60: TRUE | F60: FALSE | G60: https://www.imodis.fr/mariage/ | H60: 3 Rue du Châtelet, 67270 Saessolsheim | I60: 5h | J60: 5 | K60: 10500 | L60: 0 | M60: {=_xlfn.IFERROR(K60+L60,50000)} -> 10500 | N60: 3 | O60: du vendredi au dimanche | P60: Non | Q60: Non | R60: 200 | S60: 120 | T60: 10 | U60: 26 | V60: Non | W60: {=IF(J60<2.1,1,0)+IF(M60<'Budget - Budget'!$C$3,2,0)+IF(S60<'Invités'!$B$91,0,1)+IF(U60>'Invités'!$P$91,2,0)+IF(V60="Non",0,1)+IF(Q60="Oui",1,0)+IF(P60="Non",2,0)+IF(N60>2,2,0)+IF(M60>15000,-2,0)} -> 7 | X60: FALSE
B61: La Grange de Bourgoult | C61: TRUE | D61: TRUE | E61: TRUE | F61: FALSE | G61: https://www.mariages.net/domaine-mariage/la-grange-de-bourgoult--e7861 | H61: Harquency 27700 Les Andelys (Eure) | I61: 1h15 | J61: 1.25 | K61: {=9200+(130*5)+1800} -> 11650 | L61: {=2780+700} -> 3480 | M61: {=_xlfn.IFERROR(K61+L61,50000)} -> 15130 | N61: 3 | O61: Du Samedi au Dimanche soir 17h. Si, 5 mois avant votre mariage, le vendredi n'est pas réservé, vous pourrez avoir accès à la propriété gratuitement. + traiteur doit être sélectionné dans leur liste. | P61: Oui | Q61: Non | R61: 400 | S61: 400 | T61: 18 | U61: 71 | V61: Non | W61: {=IF(J61<2.1,1,0)+IF(M61<'Budget - Budget'!$C$3,2,0)+IF(S61<'Invités'!$B$91,0,1)+IF(U61>'Invités'!$P$91,2,0)+IF(V61="Non",0,1)+IF(Q61="Oui",1,0)+IF(P61="Non",2,0)+IF(N61>2,2,0)+IF(M61>15000,-2,0)} -> 4 | X61: FALSE
B62: Château de Serans | C62: TRUE | D62: TRUE | E62: FALSE | G62: https://www.mariages.net/chateau-mariage/chateau-de-serans--e102961 | H62: 60, Grande Rue 60240 Serans (Oise) | I62: 50min | J62: 0.83 | K62: 15000 | L62: 0 | M62: {=_xlfn.IFERROR(K62+L62,50000)} -> 15000 | O62: Trop grand pour nous | P62: Oui | Q62: Non | R62: 250 | S62: 250 | T62: ? | U62: 100 | V62: Non | W62: {=IF(J62<2.1,1,0)+IF(M62<'Budget - Budget'!$C$3,2,0)+IF(S62<'Invités'!$B$91,0,1)+IF(U62>'Invités'!$P$91,2,0)+IF(V62="Non",0,1)+IF(Q62="Oui",1,0)+IF(P62="Non",2,0)+IF(N62>2,2,0)+IF(M62>15000,-2,0)} -> 6 | X62: FALSE
B63: Les Hirondelles | C63: TRUE | D63: TRUE | E63: TRUE | F63: FALSE | G63: https://www.mariages.net/salle-mariage/les-hirondelles--e166480 | H63: 1, Route de Rochefort 78730 Longvilliers (Yvelines) | I63: 1h | J63: 1 | K63: 13500 | L63: 6648 | M63: {=_xlfn.IFERROR(K63+L63,50000)} -> 20148 | N63: 3 | O63: Vendredi 11h00 au dimanche 17h00 | P63: Non | Q63: Non | R63: 200 | S63: 200 | T63: 13 | U63: 46 | V63: Non | W63: {=IF(J63<2.1,1,0)+IF(M63<'Budget - Budget'!$C$3,2,0)+IF(S63<'Invités'!$B$91,0,1)+IF(U63>'Invités'!$P$91,2,0)+IF(V63="Non",0,1)+IF(Q63="Oui",1,0)+IF(P63="Non",2,0)+IF(N63>2,2,0)+IF(M63>15000,-2,0)} -> 4 | X63: FALSE
B64: Château de Lésigny | C64: TRUE | D64: TRUE | E64: FALSE | G64: https://www.mariages.net/chateau-mariage/chateau-de-lesigny--e141033 | H64: Chemin de la Croix 77150 Lésigny (Seine-et-Marne) | I64: 1h20 | J64: 1.33 | K64: 12000 | L64: Pas inclus donc trop cher | M64: {=_xlfn.IFERROR(K64+L64,50000)} -> 50000 | N64: 1 | O64: 1 | P64: Non | Q64: Non | R64: 300 | S64: 250 | T64: ? | U64: 120 | V64: Non | W64: {=IF(J64<2.1,1,0)+IF(M64<'Budget - Budget'!$C$3,2,0)+IF(S64<'Invités'!$B$91,0,1)+IF(U64>'Invités'!$P$91,2,0)+IF(V64="Non",0,1)+IF(Q64="Oui",1,0)+IF(P64="Non",2,0)+IF(N64>2,2,0)+IF(M64>15000,-2,0)} -> 4 | X64: FALSE
B65: La Drille au Bord de l'Eau | C65: TRUE | D65: TRUE | E65: FALSE | G65: https://www.mariages.net/domaine-mariage/la-drille-au-bord-de-leau--e375961?cmp=ADW-SEM-PMAX-VENUES&utm_source=google&utm_medium=paid-search&utm_campaign=VENUES-Pmax-B2C-Marketplace&utm_content=performance_cpm_search-ad_na_na&gclid=CjwKCAiAmp3LBhAkEiwAJM2JUNEIVpgIVYzdvy7q_9B4zPxfdHgglQ1ftklNaVrRq-QAww0pOmo2vBoCLwoQAvD_BwE | H65: 1, Rue de la Drille 67130 Wisches (Bas Rhin) | I65: 5h45 | J65: 5.75 | K65: 11900 | L65: 0 | M65: {=_xlfn.IFERROR(K65+L65,50000)} -> 11900 | N65: 4 | O65: Ve. 8h au lundi 11h | P65: Non | Q65: Non | R65: 130 | S65: 130 | T65: 12 | U65: 38 | V65: Non | W65: {=IF(J65<2.1,1,0)+IF(M65<'Budget - Budget'!$C$3,2,0)+IF(S65<'Invités'!$B$91,0,1)+IF(U65>'Invités'!$P$91,2,0)+IF(V65="Non",0,1)+IF(Q65="Oui",1,0)+IF(P65="Non",2,0)+IF(N65>2,2,0)+IF(M65>15000,-2,0)} -> 7 | X65: FALSE
B66: Château de Beauclair | C66: TRUE | D66: TRUE | E66: FALSE | G66: https://www.mariages.net/domaine-mariage/chateau-de-beauclair--e377467 | H66: Château de Beauclair 45300 Morville-en-Beauce (Loiret) | I66: 1h30 | J66: 1.5 | K66: 13000 | L66: 3000 | M66: {=_xlfn.IFERROR(K66+L66,50000)} -> 16000 | N66: 3 | O66: du vendredi 12h au dimanche 15h | P66: Non | Q66: Non | R66: 350 | S66: 350 | T66: 13 | U66: 40 | V66: Non | W66: {=IF(J66<2.1,1,0)+IF(M66<'Budget - Budget'!$C$3,2,0)+IF(S66<'Invités'!$B$91,0,1)+IF(U66>'Invités'!$P$91,2,0)+IF(V66="Non",0,1)+IF(Q66="Oui",1,0)+IF(P66="Non",2,0)+IF(N66>2,2,0)+IF(M66>15000,-2,0)} -> 6 | X66: FALSE
B67: Domaine de Montigny | C67: TRUE | D67: TRUE | E67: FALSE | G67: https://www.mariages.net/domaine-mariage/domaine-de-montigny--e180117 | H67: Butte de Montigny 60 800 Russy-Bémont (Oise) | I67: 1h25 | J67: 1.42 | K67: {=13800+490} -> 14290 | L67: 5111 | M67: {=_xlfn.IFERROR(K67+L67,50000)} -> 19401 | N67: 3 | O67: Vendredi 17h à Dimanche 17h | P67: Non | Q67: Non | R67: 600 | S67: 450 | T67: 17 | U67: 38 | V67: Non | W67: {=IF(J67<2.1,1,0)+IF(M67<'Budget - Budget'!$C$3,2,0)+IF(S67<'Invités'!$B$91,0,1)+IF(U67>'Invités'!$P$91,2,0)+IF(V67="Non",0,1)+IF(Q67="Oui",1,0)+IF(P67="Non",2,0)+IF(N67>2,2,0)+IF(M67>15000,-2,0)} -> 4 | X67: FALSE
B68: Le Domaine de Montireau | C68: TRUE | D68: TRUE | E68: FALSE | G68: https://www.mariages.net/domaine-mariage/le-domaine-de-montireau--e156376 | H68: 100, route de Champrond 28240 Montireau (Eure-et-Loir) | I68: 2h | J68: 2 | K68: 13000 | L68: 0 | M68: {=_xlfn.IFERROR(K68+L68,50000)} -> 13000 | N68: 3 | O68: du vendredi au dimanche - traiteur imposé | P68: Oui | Q68: Non | R68: 240 | S68: 240 | T68: 12 | U68: 40 | V68: Non | W68: {=IF(J68<2.1,1,0)+IF(M68<'Budget - Budget'!$C$3,2,0)+IF(S68<'Invités'!$B$91,0,1)+IF(U68>'Invités'!$P$91,2,0)+IF(V68="Non",0,1)+IF(Q68="Oui",1,0)+IF(P68="Non",2,0)+IF(N68>2,2,0)+IF(M68>15000,-2,0)} -> 6 | X68: FALSE
B69: Manoir de Corny | C69: TRUE | D69: TRUE | E69: FALSE | F69: FALSE | G69: https://www.mariages.net/domaine-mariage/manoir-de-corny--e327062 | H69: 1, Chemin de la Vieille Côte 27700 Frenelles-en-Vexin (Eure) | I69: 1h20 | J69: 1.33 | K69: {=7000+1500} -> 8500 | L69: 5050 | M69: {=_xlfn.IFERROR(K69+L69,50000)} -> 13550 | N69: 2 | O69: Du samedi au dimanche 16h - pas possible sur 3j et en plus on a pas passé d’invités | P69: Oui | Q69: Non | R69: 450 | S69: 450 | T69: 30 | U69: 116 | V69: Non | W69: {=IF(J69<2.1,1,0)+IF(M69<'Budget - Budget'!$C$3,2,0)+IF(S69<'Invités'!$B$91,0,1)+IF(U69>'Invités'!$P$91,2,0)+IF(V69="Non",0,1)+IF(Q69="Oui",1,0)+IF(P69="Non",2,0)+IF(N69>2,2,0)+IF(M69>15000,-2,0)} -> 6 | X69: FALSE
B70: Domaine des 3 voyages | C70: TRUE | D70: TRUE | E70: FALSE | G70: https://www.mariages.net/domaine-mariage/domaine-des-3-voyages--e157976 | H70: 7, Rue de Pacy 27640 Merey (Eure) | I70: 1h | J70: 1 | K70: 26650 | L70: 450 | M70: {=_xlfn.IFERROR(K70+L70,50000)} -> 27100 | N70: 3 | O70: Du vendredi au dimanche 16h - traiteur imposé, prix inclus | P70: Oui | Q70: Non | R70: 440 | S70: 150 | T70: 12 | U70: 56 | V70: Non | W70: {=IF(J70<2.1,1,0)+IF(M70<'Budget - Budget'!$C$3,2,0)+IF(S70<'Invités'!$B$91,0,1)+IF(U70>'Invités'!$P$91,2,0)+IF(V70="Non",0,1)+IF(Q70="Oui",1,0)+IF(P70="Non",2,0)+IF(N70>2,2,0)+IF(M70>15000,-2,0)} -> 2 | X70: FALSE
B71: Bona-Venture - Domaine des Aulnaies | C71: TRUE | D71: TRUE | E71: FALSE | G71: https://www.mariages.net/domaine-mariage/bona-venture-domaine-des-aulnaies--e282428 | H71: 25, Rue des Moulins 95510 Amenucourt (Val-d'Oise) | I71: 1h | J71: 1 | K71: 11800 | L71: 3900 | M71: {=_xlfn.IFERROR(K71+L71,50000)} -> 15700 | N71: 3 | O71: vendredi 14h à dimanche 17h - traiteur du lieu obligatoire | P71: Oui | Q71: Non | R71: 180 | S71: 180 | T71: 12 | U71: 42 | V71: Oui | W71: {=IF(J71<2.1,1,0)+IF(M71<'Budget - Budget'!$C$3,2,0)+IF(S71<'Invités'!$B$91,0,1)+IF(U71>'Invités'!$P$91,2,0)+IF(V71="Non",0,1)+IF(Q71="Oui",1,0)+IF(P71="Non",2,0)+IF(N71>2,2,0)+IF(M71>15000,-2,0)} -> 5 | X71: FALSE
B72: Château de la Plumasserie | C72: TRUE | D72: FALSE | E72: FALSE | G72: https://www.mariages.net/chateau-mariage/chateau-de-la-plumasserie--e271241 | H72: Route de Bellefontaine 77610 Fontenay-Trésigny (Seine-et-Marne) | I72: 1h30 | J72: 1.5 | K72: entre 6.000€ et 25.000€ | M72: {=_xlfn.IFERROR(K72+L72,50000)} -> 50000 | Q72: Non | R72: 500 | S72: 280 | T72: 60 | U72: 180 | V72: Oui | W72: {=IF(J72<2.1,1,0)+IF(M72<'Budget - Budget'!$C$3,2,0)+IF(S72<'Invités'!$B$91,0,1)+IF(U72>'Invités'!$P$91,2,0)+IF(V72="Non",0,1)+IF(Q72="Oui",1,0)+IF(P72="Non",2,0)+IF(N72>2,2,0)+IF(M72>15000,-2,0)} -> 3 | X72: FALSE
B73: Domaine de la Vallée Aux Pages | C73: TRUE | D73: TRUE | E73: TRUE | F73: FALSE | G73: https://www.mariages.net/domaine-mariage/domaine-de-la-vallee-aux-pages--e8171 | H73: 2, Rue de la Vallée - Lenainville 78660 Paray-Douaville (Yvelines) | I73: 1h15 | J73: 1.25 | K73: {=13000+1800+1760} -> 16560 | L73: 0 | M73: {=_xlfn.IFERROR(K73+L73,50000)} -> 16560 | P73: Oui | Q73: Non | R73: 310 | S73: 310 | T73: 24 | U73: 80 | V73: Oui | W73: {=IF(J73<2.1,1,0)+IF(M73<'Budget - Budget'!$C$3,2,0)+IF(S73<'Invités'!$B$91,0,1)+IF(U73>'Invités'!$P$91,2,0)+IF(V73="Non",0,1)+IF(Q73="Oui",1,0)+IF(P73="Non",2,0)+IF(N73>2,2,0)+IF(M73>15000,-2,0)} -> 5 | X73: FALSE
B74: Château de la Trye | C74: TRUE | D74: FALSE | E74: FALSE | G74: https://bridebook.com/fr/wedding-venues/ch-teau-de-la-trye-hermes-oise-fr0X22ajdX | H74: L'Abbaye de Froidmont, Hermes, Oise, 60370, Hauts-de-France, France | I74: 1h30 | J74: 1.5 | K74: 5.600€ et 14.000€ | L74: 8675 | M74: {=_xlfn.IFERROR(K74+L74,50000)} -> 50000 | Q74: Non | R74: 500 | S74: 300 | T74: 31 | U74: 79 | V74: Oui | W74: {=IF(J74<2.1,1,0)+IF(M74<'Budget - Budget'!$C$3,2,0)+IF(S74<'Invités'!$B$91,0,1)+IF(U74>'Invités'!$P$91,2,0)+IF(V74="Non",0,1)+IF(Q74="Oui",1,0)+IF(P74="Non",2,0)+IF(N74>2,2,0)+IF(M74>15000,-2,0)} -> 3 | X74: FALSE
B75: Les Hauts de Pardaillan | C75: TRUE | D75: TRUE | E75: FALSE | G75: https://www.mariages.net/domaine-mariage/les-hauts-de-pardaillan--e10685 | H75: Lieu dit la Tour Neuve - Hanches 78125 Hermeray (Yvelines) | I75: 1h15 | J75: 1.25 | K75: 23820 | M75: {=_xlfn.IFERROR(K75+L75,50000)} -> 23820 | N75: 1 | O75: 1 | P75: Non | Q75: Non | R75: 300 | S75: 250 | T75: 22 | U75: 50 | V75: Oui | W75: {=IF(J75<2.1,1,0)+IF(M75<'Budget - Budget'!$C$3,2,0)+IF(S75<'Invités'!$B$91,0,1)+IF(U75>'Invités'!$P$91,2,0)+IF(V75="Non",0,1)+IF(Q75="Oui",1,0)+IF(P75="Non",2,0)+IF(N75>2,2,0)+IF(M75>15000,-2,0)} -> 3 | X75: FALSE
B76: Le Manoir de Villefermoy | C76: TRUE | D76: TRUE | E76: FALSE | G76: https://www.mariages.net/domaine-mariage/le-manoir-de-villefermoy--e254055 | H76: Les Écrennes - Route de Fontainebleau 77820 Les Écrennes (Seine-et-Marne) | I76: 1h35 | J76: 1.58 | K76: {=12100+600} -> 12700 | L76: 3500 | M76: {=_xlfn.IFERROR(K76+L76,50000)} -> 16200 | N76: 3 | O76: Du vendredi 10h au dimanche 17h - traiteur imposé, sinon 600€ droit d’accès | P76: Oui | Q76: Non | R76: 150 | S76: 150 | T76: 21 | U76: 50 | V76: Oui | W76: {=IF(J76<2.1,1,0)+IF(M76<'Budget - Budget'!$C$3,2,0)+IF(S76<'Invités'!$B$91,0,1)+IF(U76>'Invités'!$P$91,2,0)+IF(V76="Non",0,1)+IF(Q76="Oui",1,0)+IF(P76="Non",2,0)+IF(N76>2,2,0)+IF(M76>15000,-2,0)} -> 5 | X76: FALSE
B77: Château de Rochecotte | C77: TRUE | D77: TRUE | E77: FALSE | G77: https://bridebook.com/fr/wedding-venues/ch-teau-de-rochecotte-saint-patrice-indre-et-loire-fr0og4BD8v | H77: 43, Rue Dorothée de Dino, Saint-Patrice, Indre-et-Loire, 37130, Centre-Val de Loire, France | I77: 3h30 | J77: 3.5 | K77: Sur demande | L77: 16000 | M77: {=_xlfn.IFERROR(K77+L77,50000)} -> 50000 | N77: 2 | O77: De samedi au dimanche + Ils n’acceptent pas de prestataire extérieur hormis fleurs et DJ + pas de mariage en période estivale | P77: Oui | Q77: Non | R77: 150 | S77: 120 | T77: 37 | U77: 71 | V77: Oui | W77: {=IF(J77<2.1,1,0)+IF(M77<'Budget - Budget'!$C$3,2,0)+IF(S77<'Invités'!$B$91,0,1)+IF(U77>'Invités'!$P$91,2,0)+IF(V77="Non",0,1)+IF(Q77="Oui",1,0)+IF(P77="Non",2,0)+IF(N77>2,2,0)+IF(M77>15000,-2,0)} -> 0 | X77: FALSE
B78: Linslerhof | C78: TRUE | D78: TRUE | E78: FALSE | G78: https://bridebook.com/fr/wedding-venues/kathrin-schleich-ueberherrn--de3jgyo381 | H78: Linslerhof 1, 66802 Ueberherrn, Saarland, Deutschland | I78: 4h30 | J78: 4.5 | K78: 18500 | L78: 0 | M78: {=_xlfn.IFERROR(K78+L78,50000)} -> 18500 | N78: 1 | O78: 1j et traiteur imposé | P78: Oui | Q78: Non | R78: 180 | S78: 180 | T78: 60 | U78: 110 | V78: Non | W78: {=IF(J78<2.1,1,0)+IF(M78<'Budget - Budget'!$C$3,2,0)+IF(S78<'Invités'!$B$91,0,1)+IF(U78>'Invités'!$P$91,2,0)+IF(V78="Non",0,1)+IF(Q78="Oui",1,0)+IF(P78="Non",2,0)+IF(N78>2,2,0)+IF(M78>15000,-2,0)} -> 1 | X78: FALSE
B79: Prieuré de Saint-Cyr | C79: TRUE | D79: TRUE | E79: FALSE | G79: https://www.mariages.net/domaine-mariage/prieure-de-saint-cyr--e7469 | H79: 18, Le Ru de Vrou 77750 Saint-Cyr-sur-Morin (Seine-et-Marne) | I79: 1h45 | J79: 1.75 | K79: 19000 | M79: {=_xlfn.IFERROR(K79+L79,50000)} -> 19000 | N79: 1 | O79: 1j et traiteur imposé | P79: Oui | Q79: Non | R79: 180 | S79: 180 | T79: 11 | U79: 30 | V79: Non | W79: {=IF(J79<2.1,1,0)+IF(M79<'Budget - Budget'!$C$3,2,0)+IF(S79<'Invités'!$B$91,0,1)+IF(U79>'Invités'!$P$91,2,0)+IF(V79="Non",0,1)+IF(Q79="Oui",1,0)+IF(P79="Non",2,0)+IF(N79>2,2,0)+IF(M79>15000,-2,0)} -> 0 | X79: FALSE
B80: Le Domaine de Marolles | C80: TRUE | D80: FALSE | E80: FALSE | G80: https://www.mariages.net/domaine-mariage/le-domaine-de-marolles--e148715 | H80: Lieu dit Marolles 28320 Gas (Eure-et-Loir) | I80: 1h15 | J80: 1.25 | K80: entre 2.450€ et 4.550€ | M80: {=_xlfn.IFERROR(K80+L80,50000)} -> 50000 | Q80: Non | R80: 180 | S80: 140 | T80: 10 | U80: 44 | V80: Non | W80: {=IF(J80<2.1,1,0)+IF(M80<'Budget - Budget'!$C$3,2,0)+IF(S80<'Invités'!$B$91,0,1)+IF(U80>'Invités'!$P$91,2,0)+IF(V80="Non",0,1)+IF(Q80="Oui",1,0)+IF(P80="Non",2,0)+IF(N80>2,2,0)+IF(M80>15000,-2,0)} -> 0 | X80: FALSE
B81: Château de la Confrérie | C81: TRUE | D81: TRUE | E81: FALSE | G81: https://www.mariages.net/chateau-mariage/chateau-hattonchatel--e122266?cmp=ADW-Reception-Chateau&utm_source=google&utm_medium=paid-search&utm_campaign=B2C-VENUES-Search-Marketplace&utm_content=performance_cpm_search-ad_castle_dsa_premium_na_na&gclid=CjwKCAiAmp3LBhAkEiwAJM2JUJwvaagl9NXPvST7VtZ6s4NFPfu_eoEfYXJsz6sHCX9qSm7Ge9mmORoCUdMQAvD_BwE | H81: 3 bis, Rue du Château 55210 Vigneulles-lès-Hattonchâtel (Meuse) | I81: 3h45 | J81: 3.75 | K81: 17985 | L81: 0 | M81: {=_xlfn.IFERROR(K81+L81,50000)} -> 17985 | N81: 3 | O81: du vendredi au dimanche - traiteur imposé | P81: Oui | Q81: Non | R81: 120 | S81: 120 | T81: 13 | U81: 38 | V81: Non | W81: {=IF(J81<2.1,1,0)+IF(M81<'Budget - Budget'!$C$3,2,0)+IF(S81<'Invités'!$B$91,0,1)+IF(U81>'Invités'!$P$91,2,0)+IF(V81="Non",0,1)+IF(Q81="Oui",1,0)+IF(P81="Non",2,0)+IF(N81>2,2,0)+IF(M81>15000,-2,0)} -> 1 | X81: FALSE
C82: FALSE | D82: FALSE | E82: FALSE | F82: FALSE | X82: FALSE
C83: FALSE | D83: FALSE | E83: FALSE | F83: FALSE | X83: FALSE

Sheet Repas - Tableau 1
B1: Budget/invité | C1: Budget total | D1: Commentaires | E1: Lien
A2: Repas vendredi soir | B2: {=SUM(B3:B6)} -> 26 | C2: {=SUM(C3:C6)} -> 1190
A3: Food truck - Tartes Flambées | B3: {=C3/45} -> 21 | C3: 945 | D3: De 18h00 à 21h
A4: Eau | B4: {=C4/'Invités'!$L$91} -> 0.51020408 | C4: 25
A5: Bière | B5: {=C5/'Invités'!$L$91} -> 2.4489796 | C5: 120 | D5: Fut 30L
A6: Vin | B6: {=C6/'Invités'!$L$91} -> 2.0408163 | C6: {=10*10} -> 100
A7: Repas samedi midi | B7: {=SUM(B8:B10)} -> 6.6326531 | C7: {=SUM(C8:C10)} -> 325
A8: BBQ | B8: {=C8/'Invités'!$L$91} -> 5.1020408 | C8: 250 | D8: Saucisses/Merguez, Baguettes, Coleslaw, Sauces, Désert
A9: Eau | B9: {=C9/'Invités'!$L$91} -> 0.51020408 | C9: 25
A10: Bière | B10: {=C10/'Invités'!$L$91} -> 1.0204082 | C10: 50
A11: Repas soirée de mariage | B11: {=SUM(B12:B18)} -> 119.82939 | C11: {=SUM(C12:C18)} -> 8867.375
A12: Vin d’honneur | B12: {=C12/'Invités'!$O$91} -> 17.766486 | C12: {='Repas - Gauthier traiteur'!G3+'Repas - Gauthier traiteur'!G20+'Repas - Gauthier traiteur'!G36+'Repas - Gauthier traiteur'!G62} -> 1314.72
A13: Repas | B13: {=C13/'Invités'!$O$91} -> 13.457162 | C13: {='Repas - Gauthier traiteur'!G71+'Repas - Gauthier traiteur'!G84+'Repas - Gauthier traiteur'!G87+'Repas - Gauthier traiteur'!G98+'Repas - Gauthier traiteur'!G120+'Repas - Gauthier traiteur'!G95+'Repas - Gauthier traiteur'!G133} -> 995.83
A14: Fromage | B14: {=C14/'Invités'!$O$91} -> 4.84 | C14: {='Repas - Gauthier traiteur'!G128} -> 358.16
A15: Déssert | B15: {=C15/'Invités'!$O$91} -> 6.325 | C15: {='Repas - Gauthier traiteur'!G137+'Repas - Gauthier traiteur'!G146+'Repas - Gauthier traiteur'!G154} -> 468.05
A16: Pain | B16: {=C16/'Invités'!$O$91} -> 1.1 | C16: {='Repas - Gauthier traiteur'!G159} -> 81.4
A17: Service traiteur | B17: {=C17/'Invités'!$O$91} -> 50.837838 | C17: {='Repas - Gauthier traiteur'!G189} -> 3762
A18: Vaiselle et nappage | B18: {=C18/'Invités'!$O$91} -> 25.502905 | C18: {='Repas - Gauthier traiteur'!G190} -> 1887.215
A19: Boissons repas de mariage | B19: {=SUM(B20:B26)} -> 42.994471 | C19: {=SUM(C20:C26)} -> 2680.72 | D19: Cadeau de 2000€ Hugues
A20: Soft (repas) | B20: {=C20/'Invités'!$O$91} -> 3.52 | C20: {='Repas - Gauthier traiteur'!G162} -> 260.48 | D20: Eau Minérale et Badoit en bouteilles en verre, Coca-Cola et Coca-Cola Zéro, Jus d’orange et jus de pomme, Perrier
A21: Soft (accueil) | B21: {=C21/'Invités'!$R$91} -> 2.135082 | C21: {='Repas - Gauthier traiteur'!G164} -> 130.24 | D21: Eau de Source, Sodas, Perrier, Jus de fruits
A22: Cocktail - Vin d’honneur | B22: {=C22/'Invités'!O$91} -> 0.94594595 | C22: 70 | D22: Cocktail à base de rhum - Fais par Christophe, quel contenant ?
A23: Champagne - Vin d’honneur et Dessert | B23: {=C23/'Invités'!$R$91} -> 29.508197 | C23: {=30*60} -> 1800 | D23: Blanc de Blanc
A24: Vin plat | B24: {=C24/'Invités'!$R$91} -> 1.9672131 | C24: 120
A25: Vin fromage | B25: {=C25/'Invités'!$R$91} -> 0.98360656 | C25: 60
A26: Bière soirée | B26: {=C26/'Invités'!$R$91} -> 3.9344262 | C26: {=120*2} -> 240
A27: Brunch | B27: {=SUM(B28:B33)} -> 43.215373 | C27: {=SUM(C28:C33)} -> 3841.816
A28: Veritable brunch | B28: {=C28/90} -> 19.745 | C28: {='Repas - Gauthier traiteur'!G184} -> 1777.05
A29: Service traiteur | B29: {=C29/90} -> 14.483333 | C29: {=1303.5} -> 1303.5
A30: Vaiselle et nappage | B30: {=C30/90} -> 4.2540667 | C30: {=(67.5+280.56)*1.1} -> 382.866
A31: Soft | B31: {=C31/90} -> 1.76 | C31: {=1.6*1.1*90} -> 158.4
A32: Bière | B32: {=C32/'Invités'!S$91} -> 1.6216216 | C32: 120
A33: Vin rosé | B33: {=C33/'Invités'!S$91} -> 1.3513514 | C33: {=10*10} -> 100
B34: {=B11+B19+B27+B7+B2} -> 238.67189 | C34: {=C11+C19+C27+C7+C2} -> 16904.911

Sheet Repas - Gauthier traiteur
A1: Gauthier traiteur
A2: Articles | B2: Prix unitaire HT | C2: Unité | D2: Quantités | E2: Sélectionner ? | F2: Total HT | G2: Total TTC
A3: COCKTAIL — PIÈCES FROIDES | F3: {=SUM(F4:F19)} -> 523.25 | G3: {=SUM(G4:G19)} -> 575.575
A4: Pièce déco légumes à croquer (200 pcs) + fromage blanc | B4: 125 | C4: pièce | D4: 1 | E4: Oui | F4: {=IF(E4="Oui",B4*D4,0)} -> 125 | G4: {=F4*1.1} -> 137.5
A5: Pièce déco fruits frais + brochettes (200 pcs) | B5: 135 | C5: pièce | D5: 0 | E5: Non | F5: {=IF(E5="Oui",B5*D5,0)} -> 0 | G5: {=F5*1.1} -> 0
A6: Tartines et Fingers (Saint-Jacques, canard, saumon, carotte) | B6: 1 | C6: pièce | D6: 180 | E6: Oui | F6: {=IF(E6="Oui",B6*D6,0)} -> 180 | G6: {=F6*1.1} -> 198
A7: Jolis Légumes (betterave, courgette, carotte) | B7: 1.55 | C7: pièce | D7: 0 | E7: Non | F7: {=IF(E7="Oui",B7*D7,0)} -> 0 | G7: {=F7*1.1} -> 0
A8: Millefeuille saumon fumé maison & mozzarella | B8: 1.3 | C8: pièce | D8: 45 | E8: Oui | F8: {=IF(E8="Oui",B8*D8,0)} -> 58.5 | G8: {=F8*1.1} -> 64.35
A9: Millefeuille de veau vitello Tonnato | B9: 1.3 | C9: pièce | D9: 0 | E9: Non | F9: {=IF(E9="Oui",B9*D9,0)} -> 0 | G9: {=F9*1.1} -> 0
A10: Mi cuit de thon aux sésames et soja | B10: 1.25 | C10: pièce | D10: 45 | E10: Non | F10: {=IF(E10="Oui",B10*D10,0)} -> 0 | G10: {=F10*1.1} -> 0
A11: Tataki de filet de bœuf gravlax | B11: 1.25 | C11: pièce | D11: 45 | E11: Non | F11: {=IF(E11="Oui",B11*D11,0)} -> 0 | G11: {=F11*1.1} -> 0
A12: Club crabe épicé, chou blanc, carottes, pain noir | B12: 1.3 | C12: pièce | D12: 0 | E12: Non | F12: {=IF(E12="Oui",B12*D12,0)} -> 0 | G12: {=F12*1.1} -> 0
A13: Pain aux céréales garnis en surprise (30 pcs) | B13: 28.7 | C13: pièce | D13: 0 | E13: Non | F13: {=IF(E13="Oui",B13*D13,0)} -> 0 | G13: {=F13*1.1} -> 0
A14: Œufs toqués – crème brûlée à la truffe | B14: 1.6 | C14: pièce | D14: 45 | E14: Oui | F14: {=IF(E14="Oui",B14*D14,0)} -> 72 | G14: {=F14*1.1} -> 79.2
A15: Œufs toqués – crème d'œuf et piperade, gressin | B15: 1.5 | C15: pièce | D15: 45 | E15: Non | F15: {=IF(E15="Oui",B15*D15,0)} -> 0 | G15: {=F15*1.1} -> 0
... A19: Gaspacho andalou glacé | B19: 1.35 | C19: pièce | D19: 0 | E19: Non | F19: {=IF(E19="Oui",B19*D19,0)} -> 0 | G19: {=F19*1.1} -> 0
A20: COCKTAIL — PIÈCES CHAUDES | F20: {=SUM(F21:F35)} -> 177.75 | G20: {=SUM(G21:G35)} -> 195.525
A21: Tartes fines et petits chauds (rouget, boudin noir, ris de veau…) | B21: 0.75 | C21: pièce | D21: 90 | E21: Oui | F21: {=IF(E21="Oui",B21*D21,0)} -> 67.5 | G21: {=F21*1.1} -> 74.25
A22: Pastilla de pigeon rôti, confit de fruits de saison | B22: 1.2 | C22: pièce | D22: 0 | E22: Non | F22: {=IF(E22="Oui",B22*D22,0)} -> 0 | G22: {=F22*1.1} -> 0
A23: Pastilla de daurade mi-cuite, chutney agrumes | B23: 1.2 | C23: pièce | D23: 0 | E23: Non | F23: {=IF(E23="Oui",B23*D23,0)} -> 0 | G23: {=F23*1.1} -> 0
A24: Brick de thon aux épices, accras de morue | B24: 1.2 | C24: pièce | D24: 45 | E24: Oui | F24: {=IF(E24="Oui",B24*D24,0)} -> 54 | G24: {=F24*1.1} -> 59.4
A25: Huîtres chaudes, julienne de carottes, curry léger | B25: 1.4 | C25: pièce | D25: 0 | E25: Non | F25: {=IF(E25="Oui",B25*D25,0)} -> 0 | G25: {=F25*1.1} -> 0
A26: Brochettes Saint-Jacques au lard fumé du Perche | B26: 1.95 | C26: pièce | D26: 0 | E26: Non | F26: {=IF(E26="Oui",B26*D26,0)} -> 0 | G26: {=F26*1.1} -> 0
A27: Brochettes croustillantes légumes & cochon du Perche | B27: 1.85 | C27: pièce | D27: 0 | E27: Non | F27: {=IF(E27="Oui",B27*D27,0)} -> 0 | G27: {=F27*1.1} -> 0
A28: Bonbons croustillants au foie gras chaud | B28: 1.65 | C28: pièce | D28: 45 | E28: Non | F28: {=IF(E28="Oui",B28*D28,0)} -> 0 | G28: {=F28*1.1} -> 0
A29: Burger foie gras poêlé & pommes flambées calvados | B29: 1.75 | C29: pièce | D29: 0 | E29: Non | F29: {=IF(E29="Oui",B29*D29,0)} -> 0 | G29: {=F29*1.1} -> 0
A30: Mini Bagels à la provençale | B30: 1.4 | C30: pièce | D30: 0 | E30: Non | F30: {=IF(E30="Oui",B30*D30,0)} -> 0 | G30: {=F30*1.1} -> 0
A31: Briochette aux escargots du Perche | B31: 1.25 | C31: pièce | D31: 45 | E31: Oui | F31: {=IF(E31="Oui",B31*D31,0)} -> 56.25 | G31: {=F31*1.1} -> 61.875
A32: Pipette de jus de cassis, cromesquis bleu & noix | B32: 1.25 | C32: pièce | D32: 0 | E32: Non | F32: {=IF(E32="Oui",B32*D32,0)} -> 0 | G32: {=F32*1.1} -> 0
... A35: Cuillère filet de rouget tiède, huile de persil, pickles | B35: 1.85 | C35: pièce | D35: 0 | E35: Non | F35: {=IF(E35="Oui",B35*D35,0)} -> 0 | G35: {=F35*1.1} -> 0
A36: COCKTAIL — BUFFETS À THÈMES | F36: {=SUM(F37:F61)} -> 494.2 | G36: {=SUM(G37:G61)} -> 543.62
A37: Banc d'huîtres Normandes n°3 (médaillées), pain seigle, beurre | B37: 1.35 | C37: pièce | D37: 180 | E37: Non | F37: {=IF(E37="Oui",B37*D37,0)} -> 0 | G37: {=F37*1.1} -> 0
A38: Plancha de la mer (Saint-Jacques, crevettes pesto, toasts) | B38: 2.05 | C38: pièce | D38: 0 | E38: Non | F38: {=IF(E38="Oui",B38*D38,0)} -> 0 | G38: {=F38*1.1} -> 0
A39: Dégustation saumons écossais fumés maison (blinis, crème…) | B39: 2.25 | C39: pièce | D39: 0 | E39: Non | F39: {=IF(E39="Oui",B39*D39,0)} -> 0 | G39: {=F39*1.1} -> 0
A40: Tartares de poissons sur glace (thon, bar, saumon) | B40: 1.95 | C40: pièce | D40: 0 | E40: Non | F40: {=IF(E40="Oui",B40*D40,0)} -> 0 | G40: {=F40*1.1} -> 0
A41: Les Petits Fumoirs (thon, saumon, canard, bœuf sous cloches) | B41: 1.85 | C41: pièce | D41: 45 | E41: Oui | F41: {=IF(E41="Oui",B41*D41,0)} -> 83.25 | G41: {=F41*1.1} -> 91.575
A42: Dégustation foie gras de canard (3 façons, brioche maison) | B42: 105 | C42: kg | D42: 1.35 | E42: Non | F42: {=IF(E42="Oui",B42*D42,0)} -> 0 | G42: {=F42*1.1} -> 0
A43: Buffet typiquement Percheron (boudin, terrine, jambon, rillons) | B43: 1.8 | C43: pièce | D43: 0 | E43: Non | F43: {=IF(E43="Oui",B43*D43,0)} -> 0 | G43: {=F43*1.1} -> 0
A44: Os à moelle rôtis sur pain grillé, fleur de sel | B44: 1.05 | C44: pièce | D44: 45 | E44: Non | F44: {=IF(E44="Oui",B44*D44,0)} -> 0 | G44: {=F44*1.1} -> 0
A45: Barbecue braise mini-brochettes (volaille, bœuf, magret) | B45: 1.9 | C45: pièce | D45: 0 | E45: Non | F45: {=IF(E45="Oui",B45*D45,0)} -> 0 | G45: {=F45*1.1} -> 0
A46: Foie gras poêlé devant vous, baguette du Perche | B46: 1.95 | C46: pièce | D46: 0 | E46: Non | F46: {=IF(E46="Oui",B46*D46,0)} -> 0 | G46: {=F46*1.1} -> 0
A47: Pommes de terre Rattes chaudes, escargots, foie gras | B47: 1.85 | C47: pièce | D47: 0 | E47: Non | F47: {=IF(E47="Oui",B47*D47,0)} -> 0 | G47: {=F47*1.1} -> 0
A48: Galettes & crêpes garnies sur Billig (salées et sucrées) | B48: 1.6 | C48: pièce | D48: 0 | E48: Non | F48: {=IF(E48="Oui",B48*D48,0)} -> 0 | G48: {=F48*1.1} -> 0
... A61: Assortiment de chorizo, Légumes grillés et pain à l’huile d’olive | B61: 0.98 | C61: pièce | D61: 45 | E61: Oui | F61: {=IF(E61="Oui",B61*D61,0)} -> 44.1 | G61: {=F61*1.1} -> 48.51
A62: ANIMATIONS SUCRÉES & DOUCEURS COCKTAIL | F62: {=SUM(F63:F70)} -> 0 | G62: {=SUM(G63:G70)} -> 0
A63: Smoothies & jus d'agrumes frais pressés minute | B63: 4.6 | C63: personne | D63: 0 | E63: Non | F63: {=IF(E63="Oui",B63*D63,0)} -> 0 | G63: {=F63*1.1} -> 0
A64: Voiture de glaces & sorbets à l'ancienne | B64: 1.35 | C64: pièce | D64: 0 | E64: Non | F64: {=IF(E64="Oui",B64*D64,0)} -> 0 | G64: {=F64*1.1} -> 0
A65: Barbes à papa pour enfants | B65: 1.1 | C65: pièce | D65: 0 | E65: Non | F65: {=IF(E65="Oui",B65*D65,0)} -> 0 | G65: {=F65*1.1} -> 0
A66: Mini crêpes sucrées garnies à la minute (Billig) | B66: 1.4 | C66: pièce | D66: 0 | E66: Non | F66: {=IF(E66="Oui",B66*D66,0)} -> 0 | G66: {=F66*1.1} -> 0
A67: Brochettes de fruits de saison | B67: 0.95 | C67: pièce | D67: 0 | E67: Non | F67: {=IF(E67="Oui",B67*D67,0)} -> 0 | G67: {=F67*1.1} -> 0
A68: Ananas entier en robe de fraises | B68: 45.5 | C68: pièce | D68: 0 | E68: Non | F68: {=IF(E68="Oui",B68*D68,0)} -> 0 | G68: {=F68*1.1} -> 0
A69: Assortiment fours frais (Caroline, Paris-brest, Dôme passion…) | B69: 1.1 | C69: pièce | D69: 0 | E69: Non | F69: {=IF(E69="Oui",B69*D69,0)} -> 0 | G69: {=F69*1.1} -> 0
A70: Mini macarons assortis (caramel, agrumes, fruits rouges, choco) | B70: 1 | C70: pièce | D70: 0 | E70: Non | F70: {=IF(E70="Oui",B70*D70,0)} -> 0 | G70: {=F70*1.1} -> 0
A71: REPAS — ENTRÉES LÉGÈRES | F71: {=SUM(F72:F83)} -> 0 | G71: {=SUM(G72:G83)} -> 0
A72: Tartare saumon, émulsion courgette basilic, tuile parmesan | B72: 4.2 | C72: personne | D72: {='Invités'!$O$91} -> 74 | E72: Non | F72: {=IF(E72="Oui",B72*D72,0)} -> 0 | G72: {=F72*1.1} -> 0
A73: Légumes taboulé, colin confit, vinaigrette ginger & agrumes | B73: 4.4 | C73: personne | D73: {='Invités'!$O$91} -> 74 | E73: Non | F73: {=IF(E73="Oui",B73*D73,0)} -> 0 | G73: {=F73*1.1} -> 0
A74: Bar en carpaccio, passion & vanille, tartare végétal | B74: 5.1 | C74: personne | D74: {='Invités'!$O$91} -> 74 | E74: Non | F74: {=IF(E74="Oui",B74*D74,0)} -> 0 | G74: {=F74*1.1} -> 0
A75: Saint-Jacques poêlées, vinaigrette coriandre & miel | B75: 6.6 | C75: personne | D75: {='Invités'!$O$91} -> 74 | E75: Non | F75: {=IF(E75="Oui",B75*D75,0)} -> 0 | G75: {=F75*1.1} -> 0
A76: Saint-Jacques rôties orange, purée panais vanillée, passion | B76: 6.6 | C76: personne | D76: {='Invités'!$O$91} -> 74 | E76: Non | F76: {=IF(E76="Oui",B76*D76,0)} -> 0 | G76: {=F76*1.1} -> 0
A77: Queues langoustines & Saint-Jacques, caviar courgettes, pesto | B77: 6.6 | C77: personne | D77: {='Invités'!$O$91} -> 74 | E77: Non | F77: {=IF(E77="Oui",B77*D77,0)} -> 0 | G77: {=F77*1.1} -> 0
A78: Filet de rouget rôti, tomates concassées, salade crue/cuite | B78: 4.95 | C78: personne | D78: {='Invités'!$O$91} -> 74 | E78: Non | F78: {=IF(E78="Oui",B78*D78,0)} -> 0 | G78: {=F78*1.1} -> 0
A79: Risotto crémeux, queues de langoustines rôties, sésames | B79: 6.15 | C79: personne | D79: {='Invités'!$O$91} -> 74 | E79: Non | F79: {=IF(E79="Oui",B79*D79,0)} -> 0 | G79: {=F79*1.1} -> 0
A80: Daurade plancha, caviar d'aubergine, fenouil confit | B80: 4.6 | C80: personne | D80: {='Invités'!$O$91} -> 74 | E80: Non | F80: {=IF(E80="Oui",B80*D80,0)} -> 0 | G80: {=F80*1.1} -> 0
A81: Saumon fumé maison, salade légumes croquants, asperges | B81: 4.4 | C81: personne | D81: {='Invités'!$O$91} -> 74 | E81: Non | F81: {=IF(E81="Oui",B81*D81,0)} -> 0 | G81: {=F81*1.1} -> 0
A82: Foie gras cuit au torchon, chutney pommes, pain d'épice | B82: 5.3 | C82: personne | D82: {='Invités'!$O$91} -> 74 | E82: Non | F82: {=IF(E82="Oui",B82*D82,0)} -> 0 | G82: {=F82*1.1} -> 0
A83: Foie gras cuit comme un nougat, pain fruits secs, fruits rouges | B83: 5.3 | C83: personne | D83: {='Invités'!$O$91} -> 74 | E83: Non | F83: {=IF(E83="Oui",B83*D83,0)} -> 0 | G83: {=F83*1.1} -> 0
A84: REPAS — ENTRÉES VÉGÉTALES | F84: {=SUM(F85:F86)} -> 0 | G84: {=SUM(G85:G86)} -> 0
A85: Tarte fine tiède tomates confites, mozzarella bufala, pesto | B85: 4.8 | C85: personne | D85: {='Invités'!$U$91} -> 1 | E85: Non | F85: {=IF(E85="Oui",B85*D85,0)} -> 0 | G85: {=F85*1.1} -> 0
A86: Tomate farcie de légumes crus & cuits, pétales, huile vierge | B86: 4.8 | C86: personne | D86: {='Invités'!$U$91} -> 1 | E86: Non | F86: {=IF(E86="Oui",B86*D86,0)} -> 0 | G86: {=F86*1.1} -> 0
A87: REPAS — PLATS POISSONS | F87: {=SUM(F88:F94)} -> 0 | G87: {=SUM(G88:G94)} -> 0
A88: Saumon rôti à l'estragon, écrasé pommes de terre, légumes | B88: 10.25 | C88: personne | D88: {='Invités'!$O$91} -> 74 | E88: Non | F88: {=IF(E88="Oui",B88*D88,0)} -> 0 | G88: {=F88*1.1} -> 0
A89: Cabillaud poêlé, purée carottes cumin, asperges, beurre yuzu | B89: 10.7 | C89: personne | D89: {='Invités'!$O$91} -> 74 | E89: Non | F89: {=IF(E89="Oui",B89*D89,0)} -> 0 | G89: {=F89*1.1} -> 0
A90: Daurade plancha, aubergine, fenouil, tomates cerises, polenta | B90: 10.65 | C90: personne | D90: {='Invités'!$O$91} -> 74 | E90: Non | F90: {=IF(E90="Oui",B90*D90,0)} -> 0 | G90: {=F90*1.1} -> 0
A91: Rouget soufflé, crémeux langoustines, légumes rôtis | B91: 10.65 | C91: personne | D91: {='Invités'!$O$91} -> 74 | E91: Non | F91: {=IF(E91="Oui",B91*D91,0)} -> 0 | G91: {=F91*1.1} -> 0
A92: Tonnelet de colin, bouillon végétal, pois gourmands, carotte | B92: 10.75 | C92: personne | D92: {='Invités'!$O$91} -> 74 | E92: Non | F92: {=IF(E92="Oui",B92*D92,0)} -> 0 | G92: {=F92*1.1} -> 0
A93: Bar poêlé, beurre de thym, tagliatelles de légumes | B93: 11.3 | C93: personne | D93: {='Invités'!$O$91} -> 74 | E93: Non | F93: {=IF(E93="Oui",B93*D93,0)} -> 0 | G93: {=F93*1.1} -> 0
A94: Turbot rôti sur l'arrête, champignons du moment, fenouil rôti | B94: 16.4 | C94: personne | D94: {='Invités'!$O$91} -> 74 | E94: Non | F94: {=IF(E94="Oui",B94*D94,0)} -> 0 | G94: {=F94*1.1} -> 0
A95: REPAS — PLATS VEGETAUX | F95: {=SUM(F96:F97)} -> 0 | G95: {=SUM(G96:G97)} -> 0
A96: Risotto aux champignons, légumes du potager, Chips de Parmesan | B96: 9 | C96: personne | D96: {='Invités'!$U$91} -> 1 | E96: Non | F96: {=IF(E96="Oui",B96*D96,0)} -> 0 | G96: {=F96*1.1} -> 0
A97: Purée de PdT à la truffe et légumes du sud Grillés, Crumble au thym | B97: 9 | C97: personne | D97: {='Invités'!$U$91} -> 1 | E97: Non | F97: {=IF(E97="Oui",B97*D97,0)} -> 0 | G97: {=F97*1.1} -> 0
A98: REPAS — PLATS VIANDES & VOLAILLES | F98: {=SUM(F99:F119)} -> 795.5 | G98: {=SUM(G99:G119)} -> 875.05
A99: Magret canard rôti miel Forêt du Perche & poire, légumes racines | B99: 10.75 | C99: personne | D99: {='Invités'!$O$91} -> 74 | E99: Oui | F99: {=IF(E99="Oui",B99*D99,0)} -> 795.5 | G99: {=F99*1.1} -> 875.05
A100: Magret canard rôti romarin, jus corsé, PdT fondante, carottes | B100: 10.75 | C100: personne | D100: {='Invités'!$O$91} -> 74 | E100: Non | F100: {=IF(E100="Oui",B100*D100,0)} -> 0 | G100: {=F100*1.1} -> 0
A101: Magret & foie gras de canard, galette darphin, sauce truffe | B101: 13.3 | C101: personne | D101: {='Invités'!$O$91} -> 74 | E101: Non | F101: {=IF(E101="Oui",B101*D101,0)} -> 0 | G101: {=F101*1.1} -> 0
A102: Filet pintade beurre de thym, tarte fine tomates, courgette | B102: 9.75 | C102: personne | D102: {='Invités'!$O$91} -> 74 | E102: Non | F102: {=IF(E102="Oui",B102*D102,0)} -> 0 | G102: {=F102*1.1} -> 0
A103: Filet pintade agrumes, citrons confits, purée carottes | B103: 9.75 | C103: personne | D103: {='Invités'!$O$91} -> 74 | E103: Non | F103: {=IF(E103="Oui",B103*D103,0)} -> 0 | G103: {=F103*1.1} -> 0
A104: Suprême pintade farcie foie gras & pommes, réduction cidre | B104: 11.3 | C104: personne | D104: {='Invités'!$O$91} -> 74 | E104: Non | F104: {=IF(E104="Oui",B104*D104,0)} -> 0 | G104: {=F104*1.1} -> 0
A105: Poularde Culoiseau à la Percheronne (2 façons), jus carcasse | B105: 13.3 | C105: personne | D105: {='Invités'!$O$91} -> 74 | E105: Non | F105: {=IF(E105="Oui",B105*D105,0)} -> 0 | G105: {=F105*1.1} -> 0
A106: Pigeonneau d'Anjou rôti, griottes, jus et légumes braisés | B106: 15.4 | C106: personne | D106: {='Invités'!$O$91} -> 74 | E106: Non | F106: {=IF(E106="Oui",B106*D106,0)} -> 0 | G106: {=F106*1.1} -> 0
A107: Quasi de veau basse temp., beurre estragon, purée vitelotte | B107: 12.3 | C107: personne | D107: {='Invités'!$O$91} -> 74 | E107: Non | F107: {=IF(E107="Oui",B107*D107,0)} -> 0 | G107: {=F107*1.1} -> 0
A108: Paleron de veau tout doucement, légumes grillés, gratin PdT | B108: 11.3 | C108: personne | D108: {='Invités'!$O$91} -> 74 | E108: Non | F108: {=IF(E108="Oui",B108*D108,0)} -> 0 | G108: {=F108*1.1} -> 0
A109: Filet de veau rôti, thym-romarin, PdT nouvelles, asperges | B109: 15.35 | C109: personne | D109: {='Invités'!$O$91} -> 74 | E109: Non | F109: {=IF(E109="Oui",B109*D109,0)} -> 0 | G109: {=F109*1.1} -> 0
A110: Grenadin filet veau rôti aux morilles, PdT Anna, légumes | B110: 15.35 | C110: personne | D110: {='Invités'!$O$91} -> 74 | E110: Non | F110: {=IF(E110="Oui",B110*D110,0)} -> 0 | G110: {=F110*1.1} -> 0
... A119: Duo carré & cuissot agneau romarin, ail, tian de légumes | B119: 14.3 | C119: personne | D119: {='Invités'!$O$91} -> 74 | E119: Non | F119: {=IF(E119="Oui",B119*D119,0)} -> 0 | G119: {=F119*1.1} -> 0
A120: FORMULES CONVIVIALES | F120: {=SUM(F121:F127)} -> 0 | G120: {=SUM(G121:G127)} -> 0
A121: Porcelet Vallégrain rôti à la broche + garnitures | B121: 12.9 | C121: personne | D121: {='Invités'!$O$91} -> 74 | E121: Non | F121: {=IF(E121="Oui",B121*D121,0)} -> 0 | G121: {=F121*1.1} -> 0
A122: Méchoui – agneau entier à la broche + garnitures | B122: 12.9 | C122: personne | D122: {='Invités'!$O$91} -> 74 | E122: Non | F122: {=IF(E122="Oui",B122*D122,0)} -> 0 | G122: {=F122*1.1} -> 0
A123: Côtes de bœuf au barbecue + garnitures au choix | B123: 14.55 | C123: personne | D123: {='Invités'!$O$91} -> 74 | E123: Non | F123: {=IF(E123="Oui",B123*D123,0)} -> 0 | G123: {=F123*1.1} -> 0
A124: Côte de veau double à la découpe (jus thym-romarin) | B124: 16.4 | C124: personne | D124: {='Invités'!$O$91} -> 74 | E124: Non | F124: {=IF(E124="Oui",B124*D124,0)} -> 0 | G124: {=F124*1.1} -> 0
A125: Agneau de 7h, légumes grillés, écrasé PdT aux olives | B125: 12.5 | C125: personne | D125: {='Invités'!$O$91} -> 74 | E125: Non | F125: {=IF(E125="Oui",B125*D125,0)} -> 0 | G125: {=F125*1.1} -> 0
...

Sheet Repas - Devis Food Truck
A1: Devis Food Truck
A2: Nom | B2: Type | C2: Prix | D2: Commentaires | E2: Lien
A3: Le MaquisFood | B3: Africain
A4: Afro B Food | B4: Africain
A5: Safssa African | B5: Africain | D5: Ne se déplace pas pour si peu
A6: Miam Wezon | B6: Africain
A7: Saveurs du Brésil | B7: Brésilien | D7: Trop loin, ils ne se déplacent pas à Meaucé
A8: Caramia | B8: Italien
A9: Haly Shack | B9: Italien | C9: 3150 | D9: Pour 2 food trucks (45 burgers et 45 pizzas)
A10: Vittoria pizza napoletana | B10: Italien | C10: 1550 | D10: Les conditions de privatisation sont les suivantes: - Pizzas au choix (4 à 5 pizzas au choix et à sélectionner sur la carte) : 15€/pizza TTC - Quantité minimum : 80 pizzas - Frais de prestation / privatisation : 350€ TTC
A11: La séance pizza | B11: Italien
A12: Le grand tipi | B12: Italien
A13: Tigrata Pizza | B13: Italien | D13: Pas dispo sur cette date
A14: Flamm’man | B14: Alsacien | C14: 930 | D14: 18€/pers formule à volonté avec les tartes flambées classiques + 300€ frais de déplacement (930€ pour 35 pers) | E14: Mon pref
A15: Larry’s food truck | B15: Hot dogs
A16: Burger stream | B16: Burger | D16: Pas dispo sur cette date
A17: Le tacot burger | B17: Burger | D17: Nous allons décliner votre demande, cela fait trop peu de repas au vu de la distance, nous sommes à 240kms aller/retour, c'est beaucoup de temps sur la route comparé au temps sur place.
A18: Wagy’s Burger | B18: Burger | D18: Pas dispo sur cette date
A19: L’Hambulant | B19: Burger
A20: La remorque de Gab | B20: Burger | C20: 873 | D20: Formule 1 : Burger + Frites = 13 € par personne pour 50 pers (+ frais kilométriques et privatisation) | E20: Mon pref
A21: House of Meats | B21: BBQ | C21: 1685 | D21: 16,5€/Pers + 200€ frais de staff et déplacement (menu avec 3 burgers au choix ou planche de BBQ)
A22: Wood truck | B22: Tartines | D22: Que en IDF
A23: Ty’Joh food truck | B23: Crêpe | D23: Que en IDF
A24: Burg’Eure | B24: Bagels
A25: Bagel Gourmet | B25: Bagels | D25: Leur food Truck ne se déplace pas
A26: Rest’Truck | B26: Bagels | C26: 2250 | D26: Nous ne traitons pas pour le moment les demandes de 2027. Pour 2026 les tarifs sont autour de 25 € par personne pour un brunch tout compris. pour voir la composition je vous invite à le consulter sur notre site internet resthome21.com
A27: Notre truck en plus | B27: Bagels
A28: Pancake factory | B28: Pancake
A29: La mont vinette | B29: Cocktail | C29: 2358 | D29: 1,8 verre par personne - devis modulable
A30: L’instant drink | B30: Cocktail | C30: 1496 | D30: Forfait fin d'honneur tout compris avec 2 barmans (alcool, soft, verres…) > 900€ si on prends que les 2 barmans | E30: Bien !
A31: Jungle Juice | B31: Cocktail | C31: 2800 | D31: 3 cocktail/pers - 2h pendant le vin d’honneur avec 2 barmans
A32: Bar’oof | B32: Cocktail | C32: 3139 | D32: Nous travaillons sur une base de 2,5 cocktails par personne, dont au moins 30% de mocktails, pour une durée de service de 2h. Chaque formule comprend l'ensemble des ingrédients, l'alcool, la glace et la verrerie. Nous proposons trois gammes : • Formule Découverte : 12 € TTC / cocktail et 8 € TTC / mocktail • Formule Signature : 14 € TTC / cocktail et 9 € TTC / mocktail • Formule Création : 16 € TTC / cocktail et 10 € TTC / mocktail À titre indicatif pour 90 invités (base 2,5 consommations/pers. avec 30% de mocktails) : — Découverte : 158 cocktails × 12 € + 67 mocktails × 8 € = 1 896 € + 536 € = 2 432 € TTC — Signature : 158 × 14 € + 67 × 9 € = 2 212 € + 603 € = 2 815 € TTC — Création : 158 × 16 € + 67 × 10 € = 2 528 € + 670 € = 3 198 € TTC À cela s'ajoutent : — Location du bar mobile : 180 € TTC — Frais de déplacement : 144€ TTC — Heure de service supplémentaire (au-delà des 2h) : 108 € TTC / heure
A33: Bistro sauvage | B33: Bière
A34: Le bistrot FMR | B34: Bière | D34: Se déplace pas aussi loin
A35: Le bar’bu | B35: Bière | D35: Pas dispo sur cette date
A36: Chope moi ça | B36: Bière
A37: Bière truck | B37: Bière | C37: 600 | D37: 4h avec service | E37: https://biere-truck.fr/tarifs/

Sheet Repas - Devis Brunch
A1: Devis Brunch
A2: Nom | B2: Type | C2: Prix | D2: Prix/pers | E2: Commentaires | F2: Lien
A3: Crèpes Saveurs de l'astrolabe | B3: Crêpes | C3: 1152€ | F3: saveursdelastrolabe@gmail.com
A4: Frush paris | B4: Brunch | C4: 2570 | D4: {=C4/'Invités'!$S$91} -> 34.72973 | E4: 24,90€/pers min > 2570€ pour 50 pers | F4: contact@frushparis.com
A5: Food truck Crêpes troopers | B5: Crêpes | E5: À partir de 20€/pers sans boisson pour crêpes illimités ou 15€ pour une crêpe sucrée et une crêpe salée | F5: crepestroopers@gmail.com
A6: Only brunch | B6: Brunch | C6: 2186 | E6: À partir de 26,90€/pers | F6: contact@onlybrunch.fr
A7: Ça brunch pour moi | B7: Brunch | C7: 900 | E7: 18€/pers : https://docs.google.com/spreadsheets/d/19l5phokZF2XZjeLtiz9Oy7kY7lfZbUJk4QnpF3BRvF4/edit?gid=2050704359#gid=2050704359 | F7: brunchpourmoi@gmail.com
A8: Brunch’eure | B8: Brunch | F8: https://www.bruncheure.fr/demande-de-devis
A9: Les toqués de brunch | B9: Brunch | F9: https://www.instagram.com/lestoquesdebrunchco/
A10: Collet traiteur | B10: Brunch | E10: En dehors de leur périmètre | F10: https://www.collet-traiteur.fr/public/files/69eb84aa9ec2a.pdf
A11: À votre goût | B11: Brunch | E11: En vacances à cette période | F11: https://www.avotregout.fr/services/brunch
A12: Briffaut traiteur | B12: Brunch | E12: Pas de devis sans call | F12: https://www.briffaut-traiteur.fr/
A13: Un plaisir pour les papilles | B13: Brunch | F13: https://www.facebook.com/profile.php?id=61557985466386&utm_source=ig&utm_medium=social&utm_content=link_in_bio
A14: Terroir d'épicure | B14: Brunch | F14: contact@terroir-epicure.com
A15: Xavier Hauville | B15: Brunch | E15: Ne fait pas QUE brunch | F15: https://www.groupe-hauville.com/
A16: Grand Chemin | B16: Brunch | E16: Elle envoie le devis mardi | F16: https://grandchemintraiteur.fr/
A17: Epicura | B17: Brunch | F17: https://www.epicura-receptions.fr/

Sheet Couchages - Lodge
A1: Lodge
A2: Chambre | B2: Capacité | C2: Configuration | D2: Qui ?
A3: Chambre 1 - RDC | B3: 2 | C3: 1 lit double | D3: Marie France, Alain
A4: Chambre 2 - RDC | B4: 4 | C4: 1 lit double et 2 lits simples | D4: Elisabeth, Slovqauie
A5: Chambre 1 - Étage | B5: 4 | C5: 1 lit double et 2 lits simples | D5: Danny, Valérie, Laurence, Marc
A6: Chambre 2 - Étage | B6: 4 | C6: 1 lit double et 2 lits simples | D6: Christophe, Luis, Marco, Cacotte
A7: Chambre 3 - Étage | B7: 2 | C7: 1 lit double | D7: Joseph, Marta
A8: Chambre 4 - Étage | B8: 6 | C8: 6 lits simples | D8: Théo, Claude, Maéva, Pauline, Mickael, Guy
B9: {=SUM(B3:B8)} -> 22

Sheet Couchages - Maison
A1: Maison
A2: Chambre | B2: Capacité | C2: Configuration | D2: Qui ?
A3: Chambre 1 - Louise | B3: 2 | C3: 1 lit double | D3: Léa & PA
A4: Chambre 2 - Désirée | B4: 4 | C4: 1 lits double et 2 lits simples | D4: Alena, Christophe, Amélie, Gaspard
A5: Chambre 3 - Jules | B5: 5 | C5: 1 lit double & 3 lits simples | D5: Séverine, Paul, Céline, Hugues, Constance
B6: {=SUM(B3:B5)} -> 11

Sheet Couchages - Cabane
A1: Cabane
A2: Chambre | B2: Capacité | C2: Configuration | D2: Qui ?
A3: Chambre 1 | B3: 3 | C3: 1 lit double & 1 lit simple tiroir | D3: Bilel, Lucile, Louis
B4: {=SUM(B3:B3)} -> 3

Sheet Couchages - Tipis
A1: Tipis
A2: Chambre | B2: Capacité | C2: Configuration | D2: Qui ?
A3: GLYCINE | B3: 2 | C3: 1 lit double | D3: Giresse, Marjorie
A4: ROSE | B4: 2 | C4: 1 lit double | D4: Aimé, Héléna
A5: GÉRANIUM | B5: 2 | C5: 1 lit double | D5: Loanne, Armand
A6: TULIPE | B6: 2 | C6: 1 lit double | D6: Elliot, Alina
A7: DAHLIA | B7: 2 | C7: 3 lits simples | D7: Valérie, Thierry
A8: SAULE | B8: 4 | C8: 6 lits simples | D8: Alexandre, Maximilien, Charles, Luke, Olivier, Jordan
A9: CERISIER | B9: 4 | C9: 3 lits simples | D9: Romain, Leonidas, Mélissande
A10: SAPIN | B10: 4 | C10: 3 lits simples | D10: Naza, Louise, Gabrielle
A11: FRÊNE | B11: 4 | C11: 4 lits simples | D11: Marjorie, Leya, Audrey, Clémence
A12: POIRIER | B12: 4 | C12: 1 lit double & 2 lits simples | D12: Antoine, Marion, Adrien, Noémie
A13: HÊTRE | B13: 4 | C13: 1 lit double & 2 lits simples | D13: Regis, Linda, Laurie, Amandine
A14: POMMIER | B14: 4 | C14: 1 lit double & 1 lits simples | D14: Vincent, Joelle, Victoriane
... A17: CÈDRE | B17: 4 | C17: 1 lit double & 2 lits simples | D17: Jean Marc, Marie, Elliane, Jacky
B18: {=SUM(B3:B17)} -> 50

Sheet Photos & Vidéos - Tableau 1
B1: Commentaires | C1: Prix | D1: Commentaires
A2: Photobooth | C2: 299
A3: Photo | C3: 1068 | D3: Cadeau de 500€ de Bilel
A4: Vidéo | C4: 750
C5: {=SUM(C2:C4)} -> 2117

Sheet Photos & Vidéos - Groupe photos
A1: Groupe photos

Sheet Musique
B1: Commentaires | C1: Prix | D1: Lien exemple
A2: Groupe vin d’honneur | B2: Jazz | C2: 620 | D2: MV
A3: Après repas | B3: Rock | C3: 673.34 | D3: Seven Ages
A4: DJ soirée | B4: Tout genres | C4: 1790 | D4: Maison Groovy
A5: DJ brunch | B5: House | C5: 750 | D5: Maison Groovy
A6: Total | C6: {=SUM(C2:C5)} -> 3833.34

Sheet Activités - Tableau 1
B1: Prix | C1: Commentaires | D1: Lien
A2: Wedding planner | B2: {='Activités - Devis Coordinatrice'!C4} -> 949 | C2: Pour la journée du mariage | D2: https://www.mariages.net/organisation-mariage/made-for-you-events--e245673
A3: Cours de danse | B3: 400
A4: Livre audio | B4: 80 | C4: Femme maison Groovy
A5: Arbre à empreintes | B5: 10
A6: Journal personnalisé | B6: 20
A7: Bar à croquis | B7: 750 | C7: Rachel Wang | D7: https://rachelwetk.com/
B8: {=SUM(B2:B7)} -> 2209

Sheet Activités - Devis Coordinatrice
A1: Devis Coordinatrice
A2: Nom | B2: Type | C2: Prix | D2: Commentaires | E2: Contact
A3: Claire | B3: Coordinatrice | C3: 1000 | D3: Très bon feeling par message, moins en appel. Installation de la décoration des mariés la veille du mariage (1h30/2h d’installation) + Présence de 14h le jour J jusqu’à la première danse > Pas d’assistante ? Pas sure qu’elle reste jusqu’à la première danse sans facturer d’heure sup ? | E3: Theperfectdate@outlook.fr
A4: Tiphany | B4: Coordinatrice | C4: 949 | D4: Bon feeling en appel. Vendredi présence pour briefing J-1 (18h-20h). Supervision et coordination Jour-J avec une coordinatrice (09h00 à minuit - présence jusqu’à l’ouverture de bal) = environ 15h + Présence de l’assitante (09h-16h) = 7h | E4: tiphany.madeforyou@gmail.com

Sheet Habillement
B1: Montant | C1: Lien
A2: Léa
A3: Robe mairie | B3: 300
A4: Robe église | B4: 2500
A5: Robe soirée | B5: 150
A6: Robe brunch | B6: 100
A7: Chaussures | B7: 100
A8: Accessoires | B8: 50
A9: Mise en beauté | B9: {='Coiffure_Maquillage - Devis Mak'!C8} -> 830
A10: PA
A11: Costume mairie | B11: 1000 | C11: Cadeau maman
A12: Costume église | B12: 2000
A13: Accessoires
B14: {=SUM(B3:B13)} -> 7030

Sheet Voiture
B1: Commentaires | C1: Prix | D1: Lien exemple
A2: Vendredi | B2: Voiture récente - type Porsche | C2: 750 | D2: https://www.roadstr.fr/cars/porsche-boxster-type-981-2018-marly-le-roi
A3: Samedi | B3: Vieille voiture décapotable | C3: 500 | D3: https://www.lrm-collection.fr/Location-voiture-mariage,Yvelines,page-30,78,290,.htm
A4: Total | C4: {=SUM(C2:C3)} -> 1250

Sheet Décorations - Tableau 1
B1: Budget/invité | C1: Budget total | D1: Commentaire | E1: Lien
A2: Cadeaux invités | B2: 5 | C2: {=B2*'Invités'!$O$91} -> 370
A3: Faire-part | B3: 3.86 | C3: {=B3*'Invités'!$J$91} -> 115.8
A4: Fleurs | C4: 2500
C10: {=SUM(C2:C9)} -> 2985.8

Sheet Décorations - Devis Fleuriste
A1: Devis Fleuriste
A2: Nom | B2: Type | C2: Prix | D2: Prestation | E2: Contact
A3: Ma Vie de Bohème | B3: Fleuriste | E3: contact@maviedeboheme.fr
A4: Fanny Fleurs | B4: Fleuriste | E4: contact@fannyfleurs.com
A5: Atelier Floral | B5: Fleuriste | E5: delphine.tourne@wanadoo.fr
A6: L'atelier de Fleur | B6: Fleuriste | E6: latelierdefleurd@gmail.com
A7: Caroll | B7: Fleuriste | E7: desfleursencouleurs@outlook.fr

Sheet Coiffure_Maquillage - Devis Mak
A1: Devis Makeup
A2: Nom | B2: Type | C2: Prix | D2: Prestation | E2: Contact
A3: Justine Makeup | B3: Maquillage | C3: 324 | D3: 280€ = maquillage, essai (déplacement pour le samedi : 44€) / 75€ pour le makeup d’une invitée | E3: justine.lenik@laposte.net
A4: Gaelle Gilot | B4: Maquillage | C4: 420 | D4: 350€ = maquillage, essai pour le samedi (frais de déplacement : 47€) / 90€ pour le makeup d’une invitée | E4: contact@gaellegilotmakeup.com
A5: Maeliys Make up | B5: Maquillage | C5: 375 | D5: 280€ essai et maquillage jour J / 95€ frais de déplacement / 90€ maquillage invitée | E5: maeliys_makeup28@orange.fr
A6: Eva Gelly | B6: Maquillage | C6: 480 | D6: Essai + Jour J Maquillage: 400€ / frais de déplacement 80€ / maquillage invitée : 110€ | E6: contact.evagelly@gmail.com
A7: Margaux Makeup | B7: Maquillage et coiffure | C7: 2300 | D7: Juste samedi : forfait Signature beauté de 1250€ comprend tout : le maquillage de mariée, la coiffure de mariée, les essais et et mes déplacements / Accompagnement le samedi et changement de coiffure le soir : 550€ / Forfait maquillage invité : 150€ et coiffure : 150€ / coiffure pour mairie et frais de déplacement : 500€ / coiffure brunch et frais de déplacement : 300€ | E7: margaux.frth@gmail.com
A8: Estelle Louis | B8: Maquillage et coiffure | C8: 830 | D8: Maquillage et coiffure mairie : 100€ / Déplacement 80€ / Essai, maquillage et coiffure jour j : 550€ / Changement de coiffure : 100€ / Coiffure et maquillage invitées : 110€ | E8: estelle-louis28@hotmail.fr

Sheet Coiffure_Maquillage - Devis Coi
A1: Devis Coiffure
A2: Nom | B2: Type | C2: Prix | D2: Prestation | E2: Contact
A3: Pia Paysant | B3: Coiffure | C3: 1000 | D3: essais 3 coiffures 400€ / Coiffure jour J : 250€ / Déplacement 50€ + 150€ / Changement look avant 19h : 150€ / Coiffure invitées : 90€ | E3: piapaysant@gmail.com
A4: Stéphie | B4: Coiffure | C4: 736 | D4: Coiffure marie, mariage et bouche : 160€ x 3 = 480€ + 80€ coiffure invitées / Frais de déplacement Meaucé : 48€ et Sartrouville ou Sillé : 160€ (essais inclus ? Ajouter frais de déplacement) | E4: stephie-coiffure@hotmail.com

Sheet Alliances
A1: Boutique | B1: Montant | C1: Lien
A2: Léa
A3: Diamond Factory | B3: 1500 | C3: https://www.diamondsfactory.fr/design/bague-demi-eternite-en-diamant-serti-griffes-clrn0530501
A4: PA
A5: Cartier | B5: 930 | C5: https://www.cartier.com/fr-fr/jewellery/wedding-bands/1895/alliance-1895-largeur-2-5-mm-CRB4002300
B6: {=B5+B3} -> 2430

Sheet Notaire
A1: Poste de dépense | B1: Montant
A2: Frais de notaire | B2: 233
A3: Frais de procédure | B3: 125
A4: Demande d’acte | B4: 13.99
A5: Copie d’acte obligatoire | B5: 6.99
A6: Total | B6: {=SUM(B2:B5)} -> 378.98

Sheet Lune de miel
B1: Prix | C1: Commentaires | D1: Lien
A2: A définir | B2: 5000
A3: Asie
A4: Afrique
B5: {=SUM(B2:B4)} -> 5000

Sheet  Cérémonie mairie
A1: Tableau 1

Sheet  Cérémonie religieuse - Budget
A1: Budget
B2: Prix | C2: Commentaires
A3: Préparation au mariage Sartrouville | B3: 300 | C3: Don à la paroisse
A4: Inscription mariage religieux Paroisse Saint Laumer | B4: 50 | C4: Inscription
A5: Inscription mariage religieux Paroisse Saint Laumer | B5: 350 | C5: Don à la paroisse
B6: {=B3+B4+B5} -> 700
